Workbook

Sheet Start
B2: KI wirtschaftlich einsetzen
B3: Rechenmodell zum Buch von Maximilian Rosen · Version 1.0 · Preisstand 23.10.2026 · alle Beträge netto
B5: In drei Schritten zur eigenen Rechnung
B6: 1. Öffnen Sie das Blatt „Mein Vorhaben“ (Link unten).
B7: 2. Ersetzen Sie die blau hinterlegten Beispielwerte durch Ihre eigenen Zahlen. Graue Felder rechnet die Tabelle selbst.
B8: 3. Lesen Sie Zeile „Einschätzung“ und die Hinweise. Rote Hinweise bedeuten: Eingaben prüfen.
B10: =HYPERLINK("#'Mein Vorhaben'!A1","→ Zum Blatt „Mein Vorhaben“") -> → Zum Blatt „Mein Vorhaben“
B12: Was Sie dafür brauchen
B13: Anzahl der Vorgänge je Monat, gemessene Minuten je Vorgang heute, Arbeitskosten je Stunde (Lohnbuchhaltung), Angebot des Dienstleisters mit einmaligen und laufenden Kosten.
B15: Farben
B16: Blau hinterlegt = Eingabe · Grau = Ergebnis · Grün = wichtigstes Ergebnis · Gelb (Buchblätter) = einflussreiche Annahme
B17: Formeln sind gegen versehentliches Überschreiben geschützt. Schutz aufheben: Überprüfen › Blattschutz aufheben (kein Kennwort).
B19: Weitere Blätter
B20: Die übrigen Blätter enthalten alle Rechnungen des Buches (Kapitel 3 bis 11). Eine Übersicht steht im Blatt „Anleitung“.
B22: Wichtig
B23: Frei werdende Arbeitszeit ist nicht automatisch eingespartes Geld. Die Tabelle weist beides getrennt aus.
B24: Die Ergebnisse sind Modellrechnungen mit Ihren Annahmen. Messen Sie die Werte vor einer Entscheidung im Pilotprojekt (Kapitel 11). Keine Makros, keine Datenverbindungen.

Sheet Mein Vorhaben
A1: Mein Vorhaben: Rechnet sich die KI-Anwendung?
A2: Blau hinterlegte Felder sind Eingaben: tragen Sie Ihre eigenen Werte ein. Grau hinterlegte Felder rechnet die Tabelle selbst. Alle Beträge netto. Vorbelegt ist das Beispiel aus Kapitel 5 des Buches (mittleres Volumen); „Vorsichtig“ halbiert die Zeitersparnis wie die Empfindlichkeitsrechnung im Buch.
A3: Rechenweg und Begriffe: Kapitel 5 und Anhang A des Buches. Ergebnisse sind Modellrechnungen, keine Zusage.
A5: Eingabe | B5: Vorsichtig | C5: Erwartet | D5: Ihre Variante | E5: Einheit | F5: Erläuterung
A6: Vorgänge je Monat | B6: 600 | C6: 600 | D6: 600 | E6: Anzahl | F6: Wie oft fällt der Vorgang im Monat an? Am besten zählen statt schätzen.
A7: Minuten je Vorgang heute (ohne KI) | B7: 6 | C7: 6 | D7: 6 | E7: min | F7: Gemessene Bearbeitungszeit heute, gemittelt über einfache und schwierige Fälle.
A8: Minuten je Vorgang mit KI (Prüfen und Freigeben) | B8: 4 | C8: 2 | D8: 2 | E8: min | F8: Zeit, die ein Mensch mit KI noch braucht. Vorsichtig: halbe Zeitersparnis.
A9: Anteil der Vorgänge mit Nacharbeit | B9: 0.08 | C9: 0.08 | D9: 0.08 | E9: % | F9: Wie oft muss das KI-Ergebnis korrigiert werden? Im Pilotprojekt messen.
A10: Minuten je Nacharbeit | B10: 5 | C10: 5 | D10: 5 | E10: min | F10: Zusätzliche Zeit, wenn korrigiert werden muss.
A11: Arbeitskosten je geleistete Stunde | B11: 45 | C11: 45 | D11: 45 | E11: €/h | F11: Bruttolohn plus Arbeitgeberanteile, geteilt durch tatsächlich geleistete Stunden (Blatt Arbeitskosten).
A12: KI-Kosten je Vorgang | B12: =Wirtschaftlichkeit!$C$10 -> 0.0095652174 | C12: =Wirtschaftlichkeit!$C$10 -> 0.0095652174 | D12: =Wirtschaftlichkeit!$C$10 -> 0.0095652174 | E12: € | F12: Vorbelegt aus dem Buchbeispiel (rund 1 Cent). Für eigene Werte: Blatt Vorgangsrechner oder Angebot des Dienstleisters.
A13: Feste Software- und Plattformkosten | B13: 50 | C13: 50 | D13: 50 | E13: €/Monat | F13: Monatliche Gebühren, z. B. für einen Automatisierungsdienst.
A14: Wartung und Kontrolle | B14: 4 | C14: 4 | D14: 4 | E14: h/Monat | F14: Stichproben, Anpassungen, Störungen.
A15: Neutest nach Modell- oder Anbieterwechsel | B15: 8 | C15: 8 | D15: 8 | E15: h/Jahr | F15: KI-Modelle werden regelmäßig ersetzt; danach muss neu getestet werden.
A16: Einrichtung durch Dienstleister | B16: 50 | C16: 50 | D16: 50 | E16: h | F16: Stunden laut Angebot. Richtet ein eigener Mitarbeiter ein: 0 und die Stunden unten bei den internen Stunden eintragen.
A17: Stundensatz Dienstleister | B17: 100 | C17: 100 | D17: 100 | E17: €/h | F17: Netto-Stundensatz laut Angebot.
A18: Datenschutz und Recht, einmalig | B18: 600 | C18: 600 | D18: 600 | E18: € | F18: Prüfung Auftragsverarbeitung, Verzeichnis, Information, gegebenenfalls Betriebsrat.
A19: IT-Sicherheit, einmalig | B19: 400 | C19: 400 | D19: 400 | E19: € | F19: Zugänge, Rechte, Protokollierung.
A20: Schulung | B20: 12 | C20: 12 | D20: 12 | E20: h gesamt | F20: Summe der Schulungsstunden aller Beteiligten.
A21: Interne Stunden für Auswahl, Testfälle und Pilotprojekt | B21: 16 | C21: 16 | D21: 16 | E21: h gesamt | F21: Bei eigener Einrichtung zusätzlich deren Stunden.
A22: Anteil der frei werdenden Zeit, der tatsächlich Ausgaben vermeidet | B22: 0.3 | C22: 0.3 | D22: 0.3 | E22: % | F22: Nur wenn Überstunden, Aushilfen oder Neueinstellungen wegfallen, spart frei werdende Zeit Geld. 0 % = reiner Kapazitätsgewinn.
A23: Zusätzlicher Deckungsbeitrag je Monat (optional) | B23: 0 | C23: 0 | D23: 0 | E23: €/Monat | F23: Nur Deckungsbeitrag, nicht Umsatz: z. B. bisher vergessene Leistungen, die bezahlt werden, abzüglich Material. Im Zweifel 0.
A24: Betrachtungszeitraum | B24: 24 | C24: 24 | D24: 24 | E24: Monate | F24: KI-Modelle und Preise ändern sich schnell; mehr als 36 Monate sind unsicher.
A26: Ergebnis
A27: Arbeitszeit heute | B27: =B6*B7/60 -> 60 | C27: =C6*C7/60 -> 60 | D27: =D6*D7/60 -> 60 | E27: h/Monat | F27: Vorgänge × Minuten heute.
A28: Arbeitszeit mit KI inkl. Nacharbeit und Wartung | B28: =(B6*B8+B6*B9*B10)/60+B14+B15/12 -> 48.666667 | C28: =(C6*C8+C6*C9*C10)/60+C14+C15/12 -> 28.666667 | D28: =(D6*D8+D6*D9*D10)/60+D14+D15/12 -> 28.666667 | E28: h/Monat | F28: Prüfen, Nacharbeit, Wartung und anteiliger Neutest.
A29: Frei werdende Arbeitszeit (Kapazitätsgewinn) | B29: =B27-B28 -> 11.333333 | C29: =C27-C28 -> 31.333333 | D29: =D27-D28 -> 31.333333 | E29: h/Monat | F29: Zeit, die für andere Aufgaben frei wird. Das ist noch kein Geld.
A30: Kapazitätsgewinn, mit Arbeitskosten bewertet | B30: =B29*B11 -> 510 | C30: =C29*C11 -> 1410 | D30: =D29*D11 -> 1410 | E30: €/Monat | F30: Kalkulatorischer Wert der frei werdenden Zeit.
A31: Laufende Kosten (KI und Software) | B31: =B6*B12+B13 -> 55.73913 | C31: =C6*C12+C13 -> 55.73913 | D31: =D6*D12+D13 -> 55.73913 | E31: €/Monat | F31: Zahlungswirksame Kosten je Monat.
A32: Nettoeffekt kalkulatorisch je Monat | B32: =B30-B31 -> 454.26087 | C32: =C30-C31 -> 1354.2609 | D32: =D30-D31 -> 1354.2609 | E32: €/Monat | F32: Bewertete Zeitersparnis minus laufende Kosten.
A33: Davon tatsächlich vermiedene Auszahlungen | B33: =B30*B22 -> 153 | C33: =C30*C22 -> 423 | D33: =D30*D22 -> 423 | E33: €/Monat | F33: Nur der Anteil aus Zeile 22.
A34: Nettoeffekt zahlungswirksam je Monat | B34: =B33+B23-B31 -> 97.26087 | C34: =C33+C23-C31 -> 367.26087 | D34: =D33+D23-D31 -> 367.26087 | E34: €/Monat | F34: Was am Monatsende tatsächlich auf dem Konto bleibt (inkl. Deckungsbeitrag aus Zeile 23).
A35: Einmalkosten mit Auszahlung | B35: =B16*B17+B18+B19 -> 6000 | C35: =C16*C17+C18+C19 -> 6000 | D35: =D16*D17+D18+D19 -> 6000 | E35: € | F35: Dienstleister, Datenschutz, IT-Sicherheit.
A36: Einmalkosten interne Stunden (bewertet) | B36: =(B20+B21)*B11 -> 1260 | C36: =(C20+C21)*C11 -> 1260 | D36: =(D20+D21)*D11 -> 1260 | E36: € | F36: Schulung und interne Stunden, mit Arbeitskosten bewertet.
A37: Einmalkosten gesamt | B37: =B35+B36 -> 7260 | C37: =C35+C36 -> 7260 | D37: =D35+D36 -> 7260 | E37: €
A38: Amortisation kalkulatorisch | B38: =IF(B32>0,B37/B32,"nicht erreichbar") -> 15.982006 | C38: =IF(C32>0,C37/C32,"nicht erreichbar") -> 5.3608578 | D38: =IF(D32>0,D37/D32,"nicht erreichbar") -> 5.3608578 | E38: Monate | F38: Nach wie vielen Monaten die bewertete Ersparnis alle Einmalkosten deckt.
A39: Amortisation zahlungswirksam | B39: =IF(B34>0,B35/B34,"nicht erreichbar") -> 61.689763 | C39: =IF(C34>0,C35/C34,"nicht erreichbar") -> 16.337161 | D39: =IF(D34>0,D35/D34,"nicht erreichbar") -> 16.337161 | E39: Monate | F39: Nach wie vielen Monaten die tatsächlich gesparten Auszahlungen die Einmalauszahlungen decken.
A40: Ergebnis nach Betrachtungszeitraum, kalkulatorisch | B40: =B24*B32-B37 -> 3642.2609 | C40: =C24*C32-C37 -> 25242.261 | D40: =D24*D32-D37 -> 25242.261 | E40: €
A41: Ergebnis nach Betrachtungszeitraum, zahlungswirksam | B41: =B24*B34-B35 -> -3665.7391 | C41: =C24*C34-C35 -> 2814.2609 | D41: =D24*D34-D35 -> 2814.2609 | E41: €
A42: Nettoeffekt je zusätzlichem Vorgang | B42: =(B7-B8-B9*B10)/60*B11-B12 -> 1.1904348 | C42: =(C7-C8-C9*C10)/60*C11-C12 -> 2.6904348 | D42: =(D7-D8-D9*D10)/60*D11-D12 -> 2.6904348 | E42: € | F42: Ist dieser Wert negativ, lohnt sich die Lösung bei keiner Menge.
A43: Mindestmenge, ab der sich der laufende Betrieb trägt | B43: =IF(B42>0,ROUNDUP(((B14+B15/12)*B11+B13)/B42,0),"nie") -> 219 | C43: =IF(C42>0,ROUNDUP(((C14+C15/12)*C11+C13)/C42,0),"nie") -> 97 | D43: =IF(D42>0,ROUNDUP(((D14+D15/12)*D11+D13)/D42,0),"nie") -> 97 | E43: Vorgänge | F43: Break-even ohne Einmalkosten.
A45: Einschätzung | B45: =IFERROR(IF(B6=0,"Keine Vorgänge eingetragen.",IF(B32<=0,"Rechnet sich nicht: Die bewertete Zeitersparnis deckt die laufenden Kosten nicht.",IF(B40<0,"Laufend positiv, aber die Einmalkosten werden im Betrachtungszeitraum nicht zurückverdient.",IF(B34<=0,"Kalkulatorisch lohnend. Geld spart es nur, wenn die frei werdende Zeit tatsächlich Ausgaben ersetzt.",IF(B41<0,"Kalkulatorisch lohnend; die Einmalauszahlungen werden im Betrachtungszeitraum aber nicht durch tatsächlich gesparte Ausgaben zurückverdient.","Kalkulatorisch und zahlungswirksam positiv. Annahmen im Pilotprojekt messen."))))),"Eingaben prüfen.") -> Kalkulatorisch lohnend; die Einmalauszahlungen werden im Betrachtungszeitraum aber nicht durch tatsächlich gesparte Ausgaben zurückverdient. | C45: =IFERROR(IF(C6=0,"Keine Vorgänge eingetragen.",IF(C32<=0,"Rechnet sich nicht: Die bewertete Zeitersparnis deckt die laufenden Kosten nicht.",IF(C40<0,"Laufend positiv, aber die Einmalkosten werden im Betrachtungszeitraum nicht zurückverdient.",IF(C34<=0,"Kalkulatorisch lohnend. Geld spart es nur, wenn die frei werdende Zeit tatsächlich Ausgaben ersetzt.",IF(C41<0,"Kalkulatorisch lohnend; die Einmalauszahlungen werden im Betrachtungszeitraum aber nicht durch tatsächlich gesparte Ausgaben zurückverdient.","Kalkulatorisch und zahlungswirksam positiv. Annahmen im Pilotprojekt messen."))))),"Eingaben prüfen.") -> Kalkulatorisch und zahlungswirksam positiv. Annahmen im Pilotprojekt messen. | D45: =IFERROR(IF(D6=0,"Keine Vorgänge eingetragen.",IF(D32<=0,"Rechnet sich nicht: Die bewertete Zeitersparnis deckt die laufenden Kosten nicht.",IF(D40<0,"Laufend positiv, aber die Einmalkosten werden im Betrachtungszeitraum nicht zurückverdient.",IF(D34<=0,"Kalkulatorisch lohnend. Geld spart es nur, wenn die frei werdende Zeit tatsächlich Ausgaben ersetzt.",IF(D41<0,"Kalkulatorisch lohnend; die Einmalauszahlungen werden im Betrachtungszeitraum aber nicht durch tatsächlich gesparte Ausgaben zurückverdient.","Kalkulatorisch und zahlungswirksam positiv. Annahmen im Pilotprojekt messen."))))),"Eingaben prüfen.") -> Kalkulatorisch und zahlungswirksam positiv. Annahmen im Pilotprojekt messen.
A46: Hinweise zu den Eingaben | B46: =IF((B6<=0)+(B8>=B7)+(B9>0.5)+(B7>240)+(B11<15)+(B11>150)+(B12>1)=0,"keine",IF(B6<=0,"Vorgänge fehlen. ","")&IF(B8>=B7,"Mit KI nicht schneller als heute. ","")&IF(B9>0.5,"Nacharbeit über 50 % ist sehr hoch. ","")&IF(B7>240,"Mehr als 4 Stunden je Vorgang: Einheit Minuten prüfen. ","")&IF(OR(B11<15,B11>150),"Arbeitskosten je Stunde ungewöhnlich, Blatt Arbeitskosten prüfen. ","")&IF(B12>1,"KI-Kosten über 1 € je Vorgang: Angabe prüfen.","")) -> keine | C46: =IF((C6<=0)+(C8>=C7)+(C9>0.5)+(C7>240)+(C11<15)+(C11>150)+(C12>1)=0,"keine",IF(C6<=0,"Vorgänge fehlen. ","")&IF(C8>=C7,"Mit KI nicht schneller als heute. ","")&IF(C9>0.5,"Nacharbeit über 50 % ist sehr hoch. ","")&IF(C7>240,"Mehr als 4 Stunden je Vorgang: Einheit Minuten prüfen. ","")&IF(OR(C11<15,C11>150),"Arbeitskosten je Stunde ungewöhnlich, Blatt Arbeitskosten prüfen. ","")&IF(C12>1,"KI-Kosten über 1 € je Vorgang: Angabe prüfen.","")) -> keine | D46: =IF((D6<=0)+(D8>=D7)+(D9>0.5)+(D7>240)+(D11<15)+(D11>150)+(D12>1)=0,"keine",IF(D6<=0,"Vorgänge fehlen. ","")&IF(D8>=D7,"Mit KI nicht schneller als heute. ","")&IF(D9>0.5,"Nacharbeit über 50 % ist sehr hoch. ","")&IF(D7>240,"Mehr als 4 Stunden je Vorgang: Einheit Minuten prüfen. ","")&IF(OR(D11<15,D11>150),"Arbeitskosten je Stunde ungewöhnlich, Blatt Arbeitskosten prüfen. ","")&IF(D12>1,"KI-Kosten über 1 € je Vorgang: Angabe prüfen.","")) -> keine
A48: Kalkulatorisch = frei werdende Arbeitszeit, mit Arbeitskosten bewertet. Zahlungswirksam = was tatsächlich an Ausgaben wegfällt. Eine Lösung kann kalkulatorisch lohnen und trotzdem kein Geld sparen, solange die frei werdende Zeit nicht anders genutzt wird. Umsatz zählt nie direkt, nur der Deckungsbeitrag (Zeile 23).

Sheet Anleitung
A1: Begleit-Rechenmodell: KI wirtschaftlich einsetzen
A2: Autor: Maximilian Rosen · Preisstand 23.10.2026 · Alle Preise netto, ohne Umsatzsteuer
A4: So benutzen Sie das Modell
A5: Blaue Zahlen sind Eingaben. Ändern Sie nur diese. Schwarze Zahlen sind Formeln. Grüne Zahlen holen Werte aus einem anderen Blatt.
A6: Gelb hinterlegte Zellen sind Schlüsselannahmen, die das Ergebnis stark beeinflussen. Prüfen Sie diese zuerst für Ihr Unternehmen.
A8: Blätter
A9: Parameter: Wechselkurs, Arbeitskosten, Abo-Preise und weitere Annahmen mit Quelle.
A10: Preise: API-Preise je Million Tokens. Neue Modelle oder Anbieter tragen Sie in die freien Zeilen ein.
A11: Vorgangsrechner: Kosten eines einzelnen KI-Aufrufs und pro Monat für Ihr eigenes Szenario.
A12: Rechenbeispiele: die acht durchgerechneten Beispiele aus Kapitel 3 (Tokenökonomie), nummeriert wie im Buch.
A13: Bezugsmodelle: Kapitel 4, Platz-Abo, API mit und ohne Cache, enthaltenes API-Guthaben, lokales Modell und Copilot.
A14: Arbeitskosten: Beispielrechnung der Arbeitskosten je geleistete Stunde aus Kapitel 5.
... A30: Kurzzeichen in Spalte F entsprechen weitgehend Anhang A des Buches; BE entspricht V_BE, Extern_Stundensatz entspricht S_extern, KV1 den Kosten eines korrekt erledigten Vorgangs.

Sheet Parameter
A1: Parameter und Annahmen
A3: Parameter | B3: Wert | C3: Einheit | D3: Quelle / Art
A4: Wechselkurs: US-Dollar je Euro | B4: 1.15 | C4: USD je 1 EUR | D4: Annahme, gerundet. EZB-Referenzkurs am 15.09.2026: 1,1539 USD. Vor Nutzung aktualisieren.
A5: Preisfaktor Batch-Verarbeitung | B5: 0.5 | C5: Faktor | D5: Anthropic: 50 % Rabatt auf Input und Output, gilt auch für Cache-Preise (https://platform.claude.com/docs/en/about-claude/pricing, abgerufen 23.10.2026)
A6: Arbeitskosten je geleistete Stunde | B6: 45 | C6: EUR/h | D6: Destatis, Pressemitteilung Nr. 148 vom 29.04.2026: Arbeitskosten 2025 je geleistete Stunde 45,00 EUR im Produzierenden Gewerbe und Dienstleistungsbereich (WZ-Abschnitte B bis S ohne O). https://www.destatis.de/DE/Presse/Pressemitteilungen/2026/04/PD26_148_624.html. Für kleine Betriebe oft niedriger, siehe Blatt Arbeitskosten.
A7: Arbeitstage je Monat | B7: 21 | C7: Tage | D7: Annahme
A8: Tokens je deutschem Wort | B8: 1.6 | C8: Tokens | D8: Annahme (Faustwert) für Modelle mit neuerem Tokenizer (Claude ab 4.7). Ältere Tokenizer: rund 1,6 / 1,3 = 1,23. Mit Token-Zähler des Anbieters an eigenen Texten messen.
A9: Wörter je Seite Fließtext | B9: 350 | C9: Wörter | D9: Annahme
A10: Rechenbeispiel 5: Tokens je Frage | B10: 100 | C10: Tokens | D10: Annahme
A11: Tokenizer: Mehr-Tokens der Modelle ab 4.7 gegenüber älteren | B11: 1.3 | C11: Faktor | D11: Anthropic: Modelle ab Version 4.7 erzeugen für denselben Text rund 30 % mehr Tokens (Preisseite, abgerufen 23.10.2026)
A12: Rechenbeispiel 8: Anteil komplexer Anfragen beim Routing | B12: 0.3 | C12: % | D12: Annahme
A13: Transkription: Preis je Audiominute | B13: 0.006 | C13: USD/min | D13: Annahme. Die OpenAI-Modellseite nennt für gpt-4o-transcribe Preise je Million Audio-Tokens (2,50 USD Input), keinen Minutenpreis. 0,006 USD/min ist ein in Sekundärquellen genannter Richtwert; vor Nutzung am eigenen Audio messen.
A14: ChatGPT Business, Standard-Platz, jährliche Zahlung | B14: 20 | C14: USD/Platz/Monat | D14: OpenAI Help Center, ChatGPT Business (help.openai.com/en/articles/8792828), abgerufen im Oktober 2026; monatliche Zahlung 25 USD; Premium-Platz 100/125 USD; ab zwei Plätzen; API-Nutzung nicht enthalten
A15: Claude Team, Standard-Platz, jährliche Zahlung | B15: 20 | C15: USD/Platz/Monat | D15: https://claude.com/pricing (abgerufen 23.10.2026); monatliche Zahlung 25 USD; Premium-Platz 100/125 USD
... A26: Umsatzsteuer-Regelsatz (nur zur Information) | B26: 0.19 | C26: % | D26: § 12 Abs. 1 UStG. Das Modell rechnet netto, weil vorsteuerabzugsberechtigte Unternehmen die Umsatzsteuer nicht als Kosten tragen.

Sheet Preise
A1: API-Preise je 1 Million Tokens (USD, netto)
A2: Quellen: Anthropic https://platform.claude.com/docs/en/about-claude/pricing und OpenAI-Modellseiten (siehe Hinweis), abgerufen am 23.10.2026. Momentaufnahme. Tokenizer der Anbieter unterscheiden sich; Kosten je Vorgang an eigenen Dokumenten vergleichen.
A4: Modell | B4: Input | C4: Output | D4: Cache schreiben 5 min | E4: Cache schreiben 1 h | F4: Cache-Treffer | G4: Tokenizer | H4: Hinweis
A5: Claude Haiku 5.5 | B5: 0.1 | C5: 0.5 | D5: 0.125 | E5: 0.2 | F5: 0.01 | G5: neu | H5: nur für Prompts bis 100.000 Tokens
A6: Claude Haiku 5.5 >100k | B6: 0.5 | C6: 2.5 | D6: 0.625 | E6: 1 | F6: 0.05 | G6: neu | H6: Prompt über 100.000 Tokens: gesamter Aufruf zum höheren Preis, auch Cache-Anteile
A7: Claude Sonnet 5.5 | B7: 2 | C7: 10 | D7: 2.5 | E7: 4 | F7: 0.1 | G7: neu
A8: Claude Opus 5.5 | B8: 4 | C8: 20 | D8: 5 | E8: 8 | F8: 0.2 | G8: neu
A9: Claude Fable 5.1 | B9: 10 | C9: 50 | D9: 12.5 | E9: 20 | F9: 0.25 | G9: neu | H9: Spitzenmodell; Cache-Lesen ein Vierzigstel des Input-Preises
A10: Claude Sonnet 4.6 | B10: 3 | C10: 15 | D10: 3.75 | E10: 6 | F10: 0.3 | G10: alt | H10: älterer Tokenizer: Modelle ab Version 4.7 erzeugen für denselben Text rund 30 % mehr Tokens; umgekehrt ergibt der ältere Tokenizer rund 23 % weniger (Faktor 1/1,3)
A11: Claude Haiku 4.5 | B11: 1 | C11: 5 | D11: 1.25 | E11: 2 | F11: 0.1 | G11: alt | H11: älterer Tokenizer
A12: GPT-6 Luna | B12: 0.1 | C12: 0.5 | D12: 0.125 | E12: 0 | F12: 0.01 | G12: ? | H12: OpenAI, https://developers.openai.com/api/docs/models/gpt-6-luna (abgerufen 23.10.2026); Cache-Schreiben ohne dokumentierte 1-h-Stufe; Prompt über 272.000 Tokens: Input und Cache 2-fach, Output 1,5-fach
A13: GPT-6 Luna >272k | B13: 0.2 | C13: 0.75 | D13: 0.25 | E13: 0 | F13: 0.02 | G13: ? | H13: Preisstufe für Prompts über 272.000 Tokens, gilt für den ganzen Aufruf
A14: GPT-6.1 Sol | B14: 2 | C14: 10 | D14: 2.5 | E14: 0 | F14: 0.1 | G14: ? | H14: OpenAI, https://developers.openai.com/api/docs/models/gpt-6.1-sol (abgerufen 23.10.2026); Batch und Flex 50 % günstiger; regionale Verarbeitung +10 %
A15: GPT-6.1 Sol >272k | B15: 4 | C15: 15 | D15: 5 | E15: 0 | F15: 0.2 | G15: ? | H15: Preisstufe für Prompts über 272.000 Tokens
A16: Eigenes Modell 1 | B16: 0 | C16: 0 | D16: 0 | E16: 0 | F16: 0 | H16: freie Zeile für weitere Anbieter
A17: Eigenes Modell 2 | B17: 0 | C17: 0 | D17: 0 | E17: 0 | F17: 0 | H17: freie Zeile für weitere Anbieter

Sheet Vorgangsrechner
A1: Vorgangsrechner: Was kostet ein KI-Aufruf?
A2: Tragen Sie die Werte eines typischen Aufrufs ein. Token-Zahlen erhalten Sie aus der Nutzungsanzeige des Anbieters oder per Token-Zähler.
A4: Modell | B4: Claude Sonnet 5.5 | C4: Auswahl aus Blatt Preise
A5: Input-Tokens zum normalen Preis | B5: 3000 | C5: Anweisungen, Dokumente, Frage, soweit nicht aus dem Cache
A6: zusätzlich: in Cache geschrieben (5 min) | B6: 0 | C6: nicht in der Zeile darüber enthalten; 1,25-facher Input-Preis
A7: zusätzlich: in Cache geschrieben (1 h) | B7: 0 | C7: nicht in den Zeilen darüber enthalten; 2-facher Input-Preis
A8: zusätzlich: aus dem Cache gelesen | B8: 0 | C8: nicht in den Zeilen darüber enthalten; Bruchteil des Input-Preises
A9: Output-Tokens | B9: 500 | C9: Länge der Antwort; Output ist der teuerste Posten
A10: Aufrufe je Monat | B10: 1000
A11: Batch-Verarbeitung | B11: Nein | C11: Ja = asynchron, Ergebnis später, halber Preis
A12: Abgerechnete Preisstufe (automatisch) | B12: =IF(AND(B4="Claude Haiku 5.5",B5+B6+B7+B8>100000),"Claude Haiku 5.5 >100k",IF(AND(B4="GPT-6 Luna",B5+B6+B7+B8>272000),"GPT-6 Luna >272k",IF(AND(B4="GPT-6.1 Sol",B5+B6+B7+B8>272000),"GPT-6.1 Sol >272k",B4))) -> Claude Sonnet 5.5
A13: Kosten je Aufruf (USD) | B13: =(B5*INDEX(Preise!$B$5:$B$17,MATCH(B12,Preise!$A$5:$A$17,0))+B6*INDEX(Preise!$D$5:$D$17,MATCH(B12,Preise!$A$5:$A$17,0))+B7*INDEX(Preise!$E$5:$E$17,MATCH(B12,Preise!$A$5:$A$17,0))+B8*INDEX(Preise!$F$5:$F$17,MATCH(B12,Preise!$A$5:$A$17,0))+(B9+B19)*INDEX(Preise!$C$5:$C$17,MATCH(B12,Preise!$A$5:$A$17,0)))/1000000*IF(B11="Ja",Batchfaktor,1) -> 0.011
A14: Kosten je Aufruf (EUR) | B14: =B13/USD_je_EUR -> 0.0095652174
A15: Kosten je Monat (EUR) | B15: =B14*B10 -> 9.5652174
A16: Anteil Output an den Kosten | B16: =IF(B13=0,0,(B9+B19)*INDEX(Preise!$C$5:$C$17,MATCH(B12,Preise!$A$5:$A$17,0))/1000000*IF(B11="Ja",Batchfaktor,1)/B13) -> 0.45454545
A17: Hinweis | B17: =IF(B12<>B4,"Langer Prompt: höhere Preisstufe wird angewendet","")
A19: zusätzlich: Denk-Tokens je Aufruf | B19: 0 | C19: als Output abgerechnet; bei Generation 5.5 standardmäßig an. 0 = Denken abgeschaltet oder vernachlässigbar (Haiku 5.5: disabled; Sonnet 5.5: between_tools ohne Werkzeuge)

Sheet Rechenbeispiele
A1: Rechenbeispiele aus Kapitel 3: Tokenökonomie
A2: Preise: Blatt Preise (Stand 23.10.2026). Token-Mengen sind Annahmen für typische Aufgaben, keine Messwerte. Summenzeilen sind grau.
A4: Beispiel | B4: Variante | C4: Modell | D4: Input ohne Cache | E4: Cache schreiben 5 min | F4: Cache schreiben 1 h | G4: Cache-Treffer | H4: Output | I4: Aufrufe je Monat | J4: Batch | K4: Kosten je Aufruf (USD) | L4: Kosten je Monat (USD) | M4: Kosten je Monat (EUR) | N4: Erläuterung
A5: 1 | B5: Ein einzelner Aufruf | C5: Claude Sonnet 5.5 | D5: 1200 | E5: 0 | F5: 0 | G5: 0 | H5: 400 | I5: 1 | J5: Nein | K5: =(D5*INDEX(Preise!$B$5:$B$17,MATCH(C5,Preise!$A$5:$A$17,0))+E5*INDEX(Preise!$D$5:$D$17,MATCH(C5,Preise!$A$5:$A$17,0))+F5*INDEX(Preise!$E$5:$E$17,MATCH(C5,Preise!$A$5:$A$17,0))+G5*INDEX(Preise!$F$5:$F$17,MATCH(C5,Preise!$A$5:$A$17,0))+H5*INDEX(Preise!$C$5:$C$17,MATCH(C5,Preise!$A$5:$A$17,0)))/1000000*IF(J5="Ja",Batchfaktor,1) -> 0.0064 | L5: =K5*I5 -> 0.0064 | M5: =L5/USD_je_EUR -> 0.0055652174 | N5: Kurze Anfrage mit kurzer Antwort: kaum messbare Kosten.
A6: 1 | B6: 50 Aufrufe je Arbeitstag | C6: Claude Sonnet 5.5 | D6: 1200 | E6: 0 | F6: 0 | G6: 0 | H6: 400 | I6: =50*Arbeitstage -> 1050 | J6: Nein | K6: =(D6*INDEX(Preise!$B$5:$B$17,MATCH(C6,Preise!$A$5:$A$17,0))+E6*INDEX(Preise!$D$5:$D$17,MATCH(C6,Preise!$A$5:$A$17,0))+F6*INDEX(Preise!$E$5:$E$17,MATCH(C6,Preise!$A$5:$A$17,0))+G6*INDEX(Preise!$F$5:$F$17,MATCH(C6,Preise!$A$5:$A$17,0))+H6*INDEX(Preise!$C$5:$C$17,MATCH(C6,Preise!$A$5:$A$17,0)))/1000000*IF(J6="Ja",Batchfaktor,1) -> 0.0064 | L6: =K6*I6 -> 6.72 | M6: =L6/USD_je_EUR -> 5.8434783 | N6: Derselbe Prompt in einem kleinen Team.
A7: 1 | B7: 2.000 Aufrufe je Arbeitstag | C7: Claude Sonnet 5.5 | D7: 1200 | E7: 0 | F7: 0 | G7: 0 | H7: 400 | I7: =2000*Arbeitstage -> 42000 | J7: Nein | K7: =(D7*INDEX(Preise!$B$5:$B$17,MATCH(C7,Preise!$A$5:$A$17,0))+E7*INDEX(Preise!$D$5:$D$17,MATCH(C7,Preise!$A$5:$A$17,0))+F7*INDEX(Preise!$E$5:$E$17,MATCH(C7,Preise!$A$5:$A$17,0))+G7*INDEX(Preise!$F$5:$F$17,MATCH(C7,Preise!$A$5:$A$17,0))+H7*INDEX(Preise!$C$5:$C$17,MATCH(C7,Preise!$A$5:$A$17,0)))/1000000*IF(J7="Ja",Batchfaktor,1) -> 0.0064 | L7: =K7*I7 -> 268.8 | M7: =L7/USD_je_EUR -> 233.73913 | N7: Derselbe Prompt in einer automatisierten Verarbeitung.
A8: 2 | B8: Kurze Antwort (300 Tokens) | C8: Claude Sonnet 5.5 | D8: 2000 | E8: 0 | F8: 0 | G8: 0 | H8: 300 | I8: 3000 | J8: Nein | K8: =(D8*INDEX(Preise!$B$5:$B$17,MATCH(C8,Preise!$A$5:$A$17,0))+E8*INDEX(Preise!$D$5:$D$17,MATCH(C8,Preise!$A$5:$A$17,0))+F8*INDEX(Preise!$E$5:$E$17,MATCH(C8,Preise!$A$5:$A$17,0))+G8*INDEX(Preise!$F$5:$F$17,MATCH(C8,Preise!$A$5:$A$17,0))+H8*INDEX(Preise!$C$5:$C$17,MATCH(C8,Preise!$A$5:$A$17,0)))/1000000*IF(J8="Ja",Batchfaktor,1) -> 0.007 | L8: =K8*I8 -> 21 | M8: =L8/USD_je_EUR -> 18.26087 | N8: Gleiche Aufgabe, Antwort auf das Nötige begrenzt.
A9: 2 | B9: Ausführliche Antwort (1.500 Tokens) | C9: Claude Sonnet 5.5 | D9: 2000 | E9: 0 | F9: 0 | G9: 0 | H9: 1500 | I9: 3000 | J9: Nein | K9: =(D9*INDEX(Preise!$B$5:$B$17,MATCH(C9,Preise!$A$5:$A$17,0))+E9*INDEX(Preise!$D$5:$D$17,MATCH(C9,Preise!$A$5:$A$17,0))+F9*INDEX(Preise!$E$5:$E$17,MATCH(C9,Preise!$A$5:$A$17,0))+G9*INDEX(Preise!$F$5:$F$17,MATCH(C9,Preise!$A$5:$A$17,0))+H9*INDEX(Preise!$C$5:$C$17,MATCH(C9,Preise!$A$5:$A$17,0)))/1000000*IF(J9="Ja",Batchfaktor,1) -> 0.019 | L9: =K9*I9 -> 57 | M9: =L9/USD_je_EUR -> 49.565217 | N9: Output kostet je Token das Fünffache des Inputs.
A10: 3 | B10: Prompt 99.000 Tokens | C10: Claude Haiku 5.5 | D10: 99000 | E10: 0 | F10: 0 | G10: 0 | H10: 1000 | I10: 1 | J10: Nein | K10: =(D10*INDEX(Preise!$B$5:$B$17,MATCH(C10,Preise!$A$5:$A$17,0))+E10*INDEX(Preise!$D$5:$D$17,MATCH(C10,Preise!$A$5:$A$17,0))+F10*INDEX(Preise!$E$5:$E$17,MATCH(C10,Preise!$A$5:$A$17,0))+G10*INDEX(Preise!$F$5:$F$17,MATCH(C10,Preise!$A$5:$A$17,0))+H10*INDEX(Preise!$C$5:$C$17,MATCH(C10,Preise!$A$5:$A$17,0)))/1000000*IF(J10="Ja",Batchfaktor,1) -> 0.0104 | L10: =K10*I10 -> 0.0104 | M10: =L10/USD_je_EUR -> 0.0090434783 | N10: Knapp unter der Preisschwelle.
A11: 3 | B11: Prompt 101.000 Tokens | C11: Claude Haiku 5.5 >100k | D11: 101000 | E11: 0 | F11: 0 | G11: 0 | H11: 1000 | I11: 1 | J11: Nein | K11: =(D11*INDEX(Preise!$B$5:$B$17,MATCH(C11,Preise!$A$5:$A$17,0))+E11*INDEX(Preise!$D$5:$D$17,MATCH(C11,Preise!$A$5:$A$17,0))+F11*INDEX(Preise!$E$5:$E$17,MATCH(C11,Preise!$A$5:$A$17,0))+G11*INDEX(Preise!$F$5:$F$17,MATCH(C11,Preise!$A$5:$A$17,0))+H11*INDEX(Preise!$C$5:$C$17,MATCH(C11,Preise!$A$5:$A$17,0)))/1000000*IF(J11="Ja",Batchfaktor,1) -> 0.053 | L11: =K11*I11 -> 0.053 | M11: =L11/USD_je_EUR -> 0.046086957 | N11: 2 % mehr Input, gesamter Aufruf zum fünffachen Preis.
A12: 4 | B12: Vorgänger, älterer Tokenizer | C12: Claude Sonnet 4.6 | D12: =ROUND(10000*Token_je_Wort/Tokenizer_Faktor_alt,-2) -> 12300 | E12: 0 | F12: 0 | G12: 0 | H12: 0 | I12: 1 | J12: Nein | K12: =(D12*INDEX(Preise!$B$5:$B$17,MATCH(C12,Preise!$A$5:$A$17,0))+E12*INDEX(Preise!$D$5:$D$17,MATCH(C12,Preise!$A$5:$A$17,0))+F12*INDEX(Preise!$E$5:$E$17,MATCH(C12,Preise!$A$5:$A$17,0))+G12*INDEX(Preise!$F$5:$F$17,MATCH(C12,Preise!$A$5:$A$17,0))+H12*INDEX(Preise!$C$5:$C$17,MATCH(C12,Preise!$A$5:$A$17,0)))/1000000*IF(J12="Ja",Batchfaktor,1) -> 0.0369 | L12: =K12*I12 -> 0.0369 | M12: =L12/USD_je_EUR -> 0.032086957 | N12: 10.000 Wörter Input; der ältere Tokenizer erzeugt 1/1,3 der Tokens des neueren, also rund 23 % weniger.
A13: 4 | B13: Nachfolger, neuerer Tokenizer (+30 %) | C13: Claude Sonnet 5.5 | D13: =ROUND(10000*Token_je_Wort,-2) -> 16000 | E13: 0 | F13: 0 | G13: 0 | H13: 0 | I13: 1 | J13: Nein | K13: =(D13*INDEX(Preise!$B$5:$B$17,MATCH(C13,Preise!$A$5:$A$17,0))+E13*INDEX(Preise!$D$5:$D$17,MATCH(C13,Preise!$A$5:$A$17,0))+F13*INDEX(Preise!$E$5:$E$17,MATCH(C13,Preise!$A$5:$A$17,0))+G13*INDEX(Preise!$F$5:$F$17,MATCH(C13,Preise!$A$5:$A$17,0))+H13*INDEX(Preise!$C$5:$C$17,MATCH(C13,Preise!$A$5:$A$17,0)))/1000000*IF(J13="Ja",Batchfaktor,1) -> 0.032 | L13: =K13*I13 -> 0.032 | M13: =L13/USD_je_EUR -> 0.027826087 | N13: Gleicher Text, laut Anbieter rund 30 % mehr Tokens. Listenpreis −33 %, tatsächliche Kosten nur rund −13 %.
A14: 5 | B14: Handbuch bei jeder Frage, ohne Cache | C14: Claude Sonnet 5.5 | D14: =ROUND(80*Woerter_je_Seite*Token_je_Wort,-3)+Tokens_je_Frage -> 45100 | E14: 0 | F14: 0 | G14: 0 | H14: 400 | I14: =20*Arbeitstage -> 420 | J14: Nein | K14: =(D14*INDEX(Preise!$B$5:$B$17,MATCH(C14,Preise!$A$5:$A$17,0))+E14*INDEX(Preise!$D$5:$D$17,MATCH(C14,Preise!$A$5:$A$17,0))+F14*INDEX(Preise!$E$5:$E$17,MATCH(C14,Preise!$A$5:$A$17,0))+G14*INDEX(Preise!$F$5:$F$17,MATCH(C14,Preise!$A$5:$A$17,0))+H14*INDEX(Preise!$C$5:$C$17,MATCH(C14,Preise!$A$5:$A$17,0)))/1000000*IF(J14="Ja",Batchfaktor,1) -> 0.0942 | L14: =K14*I14 -> 39.564 | M14: =L14/USD_je_EUR -> 34.403478 | N14: 80 Seiten Handbuch plus Frage, 20 Fragen je Tag, Abstand rund 24 Minuten.
A15: 5 | B15: 5-min-Cache bei 24 min Abstand | C15: Claude Sonnet 5.5 | D15: =Tokens_je_Frage -> 100 | E15: =ROUND(80*Woerter_je_Seite*Token_je_Wort,-3) -> 45000 | F15: 0 | G15: 0 | H15: 400 | I15: =20*Arbeitstage -> 420 | J15: Nein | K15: =(D15*INDEX(Preise!$B$5:$B$17,MATCH(C15,Preise!$A$5:$A$17,0))+E15*INDEX(Preise!$D$5:$D$17,MATCH(C15,Preise!$A$5:$A$17,0))+F15*INDEX(Preise!$E$5:$E$17,MATCH(C15,Preise!$A$5:$A$17,0))+G15*INDEX(Preise!$F$5:$F$17,MATCH(C15,Preise!$A$5:$A$17,0))+H15*INDEX(Preise!$C$5:$C$17,MATCH(C15,Preise!$A$5:$A$17,0)))/1000000*IF(J15="Ja",Batchfaktor,1) -> 0.1167 | L15: =K15*I15 -> 49.014 | M15: =L15/USD_je_EUR -> 42.62087 | N15: Cache läuft zwischen zwei Fragen ab: jeder Aufruf schreibt neu und zahlt 25 % Aufschlag.
A16: 5 | B16: 1-h-Cache: erster Aufruf am Tag | C16: Claude Sonnet 5.5 | D16: =Tokens_je_Frage -> 100 | E16: 0 | F16: =ROUND(80*Woerter_je_Seite*Token_je_Wort,-3) -> 45000 | G16: 0 | H16: 400 | I16: =Arbeitstage -> 21 | J16: Nein | K16: =(D16*INDEX(Preise!$B$5:$B$17,MATCH(C16,Preise!$A$5:$A$17,0))+E16*INDEX(Preise!$D$5:$D$17,MATCH(C16,Preise!$A$5:$A$17,0))+F16*INDEX(Preise!$E$5:$E$17,MATCH(C16,Preise!$A$5:$A$17,0))+G16*INDEX(Preise!$F$5:$F$17,MATCH(C16,Preise!$A$5:$A$17,0))+H16*INDEX(Preise!$C$5:$C$17,MATCH(C16,Preise!$A$5:$A$17,0)))/1000000*IF(J16="Ja",Batchfaktor,1) -> 0.1842 | L16: =K16*I16 -> 3.8682 | M16: =L16/USD_je_EUR -> 3.3636522 | N16: Einmal täglich schreiben (2-facher Input-Preis).
A17: 5 | B17: 1-h-Cache: Folgeaufrufe | C17: Claude Sonnet 5.5 | D17: =Tokens_je_Frage -> 100 | E17: 0 | F17: 0 | G17: =ROUND(80*Woerter_je_Seite*Token_je_Wort,-3) -> 45000 | H17: 400 | I17: =19*Arbeitstage -> 399 | J17: Nein | K17: =(D17*INDEX(Preise!$B$5:$B$17,MATCH(C17,Preise!$A$5:$A$17,0))+E17*INDEX(Preise!$D$5:$D$17,MATCH(C17,Preise!$A$5:$A$17,0))+F17*INDEX(Preise!$E$5:$E$17,MATCH(C17,Preise!$A$5:$A$17,0))+G17*INDEX(Preise!$F$5:$F$17,MATCH(C17,Preise!$A$5:$A$17,0))+H17*INDEX(Preise!$C$5:$C$17,MATCH(C17,Preise!$A$5:$A$17,0)))/1000000*IF(J17="Ja",Batchfaktor,1) -> 0.0087 | L17: =K17*I17 -> 3.4713 | M17: =L17/USD_je_EUR -> 3.0185217 | N17: Treffer verlängern den Cache; Annahme: keine Pause über 60 Minuten.
B18: Summe 1-h-Cache | L18: =SUM(L16:L17) -> 7.3395 | M18: =SUM(M16:M17) -> 6.3821739 | N18: Variante mit 1-h-Cache gesamt.
A19: 5 | B19: Nur passende Abschnitte (RAG) | C19: Claude Sonnet 5.5 | D19: =4000+Tokens_je_Frage -> 4100 | E19: 0 | F19: 0 | G19: 0 | H19: 400 | I19: =20*Arbeitstage -> 420 | J19: Nein | K19: =(D19*INDEX(Preise!$B$5:$B$17,MATCH(C19,Preise!$A$5:$A$17,0))+E19*INDEX(Preise!$D$5:$D$17,MATCH(C19,Preise!$A$5:$A$17,0))+F19*INDEX(Preise!$E$5:$E$17,MATCH(C19,Preise!$A$5:$A$17,0))+G19*INDEX(Preise!$F$5:$F$17,MATCH(C19,Preise!$A$5:$A$17,0))+H19*INDEX(Preise!$C$5:$C$17,MATCH(C19,Preise!$A$5:$A$17,0)))/1000000*IF(J19="Ja",Batchfaktor,1) -> 0.0122 | L19: =K19*I19 -> 5.124 | M19: =L19/USD_je_EUR -> 4.4556522 | N19: Suche liefert rund 4.000 Tokens passender Textstellen; Kosten für Suche und Index nicht enthalten.
A20: 6 | B20: Sofortverarbeitung, kleines Modell | C20: Claude Haiku 5.5 | D20: 3500 | E20: 0 | F20: 0 | G20: 0 | H20: 400 | I20: 2000 | J20: Nein | K20: =(D20*INDEX(Preise!$B$5:$B$17,MATCH(C20,Preise!$A$5:$A$17,0))+E20*INDEX(Preise!$D$5:$D$17,MATCH(C20,Preise!$A$5:$A$17,0))+F20*INDEX(Preise!$E$5:$E$17,MATCH(C20,Preise!$A$5:$A$17,0))+G20*INDEX(Preise!$F$5:$F$17,MATCH(C20,Preise!$A$5:$A$17,0))+H20*INDEX(Preise!$C$5:$C$17,MATCH(C20,Preise!$A$5:$A$17,0)))/1000000*IF(J20="Ja",Batchfaktor,1) -> 0.00055 | L20: =K20*I20 -> 1.1 | M20: =L20/USD_je_EUR -> 0.95652174 | N20: Datenauszug aus 2.000 Dokumenten je Monat.
A21: 6 | B21: Batch, kleines Modell | C21: Claude Haiku 5.5 | D21: 3500 | E21: 0 | F21: 0 | G21: 0 | H21: 400 | I21: 2000 | J21: Ja | K21: =(D21*INDEX(Preise!$B$5:$B$17,MATCH(C21,Preise!$A$5:$A$17,0))+E21*INDEX(Preise!$D$5:$D$17,MATCH(C21,Preise!$A$5:$A$17,0))+F21*INDEX(Preise!$E$5:$E$17,MATCH(C21,Preise!$A$5:$A$17,0))+G21*INDEX(Preise!$F$5:$F$17,MATCH(C21,Preise!$A$5:$A$17,0))+H21*INDEX(Preise!$C$5:$C$17,MATCH(C21,Preise!$A$5:$A$17,0)))/1000000*IF(J21="Ja",Batchfaktor,1) -> 0.000275 | L21: =K21*I21 -> 0.55 | M21: =L21/USD_je_EUR -> 0.47826087 | N21: Halber Preis; absolute Ersparnis sehr klein.
A22: 6 | B22: Sofortverarbeitung, mittleres Modell | C22: Claude Sonnet 5.5 | D22: 3500 | E22: 0 | F22: 0 | G22: 0 | H22: 400 | I22: 2000 | J22: Nein | K22: =(D22*INDEX(Preise!$B$5:$B$17,MATCH(C22,Preise!$A$5:$A$17,0))+E22*INDEX(Preise!$D$5:$D$17,MATCH(C22,Preise!$A$5:$A$17,0))+F22*INDEX(Preise!$E$5:$E$17,MATCH(C22,Preise!$A$5:$A$17,0))+G22*INDEX(Preise!$F$5:$F$17,MATCH(C22,Preise!$A$5:$A$17,0))+H22*INDEX(Preise!$C$5:$C$17,MATCH(C22,Preise!$A$5:$A$17,0)))/1000000*IF(J22="Ja",Batchfaktor,1) -> 0.011 | L22: =K22*I22 -> 22 | M22: =L22/USD_je_EUR -> 19.130435
A23: 6 | B23: Batch, mittleres Modell | C23: Claude Sonnet 5.5 | D23: 3500 | E23: 0 | F23: 0 | G23: 0 | H23: 400 | I23: 2000 | J23: Ja | K23: =(D23*INDEX(Preise!$B$5:$B$17,MATCH(C23,Preise!$A$5:$A$17,0))+E23*INDEX(Preise!$D$5:$D$17,MATCH(C23,Preise!$A$5:$A$17,0))+F23*INDEX(Preise!$E$5:$E$17,MATCH(C23,Preise!$A$5:$A$17,0))+G23*INDEX(Preise!$F$5:$F$17,MATCH(C23,Preise!$A$5:$A$17,0))+H23*INDEX(Preise!$C$5:$C$17,MATCH(C23,Preise!$A$5:$A$17,0)))/1000000*IF(J23="Ja",Batchfaktor,1) -> 0.0055 | L23: =K23*I23 -> 11 | M23: =L23/USD_je_EUR -> 9.5652174
A24: 7 | B24: Tabelle komplett im Prompt | C24: Claude Sonnet 5.5 | D24: 500000 | E24: 0 | F24: 0 | G24: 0 | H24: 1500 | I24: 20 | J24: Nein | K24: =(D24*INDEX(Preise!$B$5:$B$17,MATCH(C24,Preise!$A$5:$A$17,0))+E24*INDEX(Preise!$D$5:$D$17,MATCH(C24,Preise!$A$5:$A$17,0))+F24*INDEX(Preise!$E$5:$E$17,MATCH(C24,Preise!$A$5:$A$17,0))+G24*INDEX(Preise!$F$5:$F$17,MATCH(C24,Preise!$A$5:$A$17,0))+H24*INDEX(Preise!$C$5:$C$17,MATCH(C24,Preise!$A$5:$A$17,0)))/1000000*IF(J24="Ja",Batchfaktor,1) -> 1.015 | L24: =K24*I24 -> 20.3 | M24: =L24/USD_je_EUR -> 17.652174 | N24: 20.000 Zeilen mit je rund 25 Tokens; Rechnen im Modell ist zudem fehleranfällig.
A25: 7 | B25: Nur Spalten und Stichprobe, Modell schreibt Code | C25: Claude Sonnet 5.5 | D25: 3000 | E25: 0 | F25: 0 | G25: 0 | H25: 800 | I25: 20 | J25: Nein | K25: =(D25*INDEX(Preise!$B$5:$B$17,MATCH(C25,Preise!$A$5:$A$17,0))+E25*INDEX(Preise!$D$5:$D$17,MATCH(C25,Preise!$A$5:$A$17,0))+F25*INDEX(Preise!$E$5:$E$17,MATCH(C25,Preise!$A$5:$A$17,0))+G25*INDEX(Preise!$F$5:$F$17,MATCH(C25,Preise!$A$5:$A$17,0))+H25*INDEX(Preise!$C$5:$C$17,MATCH(C25,Preise!$A$5:$A$17,0)))/1000000*IF(J25="Ja",Batchfaktor,1) -> 0.014 | L25: =K25*I25 -> 0.28 | M25: =L25/USD_je_EUR -> 0.24347826 | N25: Berechnung läuft in Python oder SQL außerhalb des Modells.
A26: 8 | B26: Alles mit mittlerem Modell | C26: Claude Sonnet 5.5 | D26: 2500 | E26: 0 | F26: 0 | G26: 0 | H26: 500 | I26: 3000 | J26: Nein | K26: =(D26*INDEX(Preise!$B$5:$B$17,MATCH(C26,Preise!$A$5:$A$17,0))+E26*INDEX(Preise!$D$5:$D$17,MATCH(C26,Preise!$A$5:$A$17,0))+F26*INDEX(Preise!$E$5:$E$17,MATCH(C26,Preise!$A$5:$A$17,0))+G26*INDEX(Preise!$F$5:$F$17,MATCH(C26,Preise!$A$5:$A$17,0))+H26*INDEX(Preise!$C$5:$C$17,MATCH(C26,Preise!$A$5:$A$17,0)))/1000000*IF(J26="Ja",Batchfaktor,1) -> 0.01 | L26: =K26*I26 -> 30 | M26: =L26/USD_je_EUR -> 26.086957 | N26: Kundenanfragen einordnen und Antwort entwerfen.
A27: 8 | B27: Alles mit großem Modell | C27: Claude Opus 5.5 | D27: 2500 | E27: 0 | F27: 0 | G27: 0 | H27: 500 | I27: 3000 | J27: Nein | K27: =(D27*INDEX(Preise!$B$5:$B$17,MATCH(C27,Preise!$A$5:$A$17,0))+E27*INDEX(Preise!$D$5:$D$17,MATCH(C27,Preise!$A$5:$A$17,0))+F27*INDEX(Preise!$E$5:$E$17,MATCH(C27,Preise!$A$5:$A$17,0))+G27*INDEX(Preise!$F$5:$F$17,MATCH(C27,Preise!$A$5:$A$17,0))+H27*INDEX(Preise!$C$5:$C$17,MATCH(C27,Preise!$A$5:$A$17,0)))/1000000*IF(J27="Ja",Batchfaktor,1) -> 0.02 | L27: =K27*I27 -> 60 | M27: =L27/USD_je_EUR -> 52.173913
A28: 8 | B28: Routing: Einordnung kleines Modell | C28: Claude Haiku 5.5 | D28: 2500 | E28: 0 | F28: 0 | G28: 0 | H28: 50 | I28: 3000 | J28: Nein | K28: =(D28*INDEX(Preise!$B$5:$B$17,MATCH(C28,Preise!$A$5:$A$17,0))+E28*INDEX(Preise!$D$5:$D$17,MATCH(C28,Preise!$A$5:$A$17,0))+F28*INDEX(Preise!$E$5:$E$17,MATCH(C28,Preise!$A$5:$A$17,0))+G28*INDEX(Preise!$F$5:$F$17,MATCH(C28,Preise!$A$5:$A$17,0))+H28*INDEX(Preise!$C$5:$C$17,MATCH(C28,Preise!$A$5:$A$17,0)))/1000000*IF(J28="Ja",Batchfaktor,1) -> 0.000275 | L28: =K28*I28 -> 0.825 | M28: =L28/USD_je_EUR -> 0.7173913 | N28: Jede Anfrage wird zuerst eingeordnet.
A29: 8 | B29: Routing: 30 % komplexe Fälle | C29: Claude Sonnet 5.5 | D29: 2500 | E29: 0 | F29: 0 | G29: 0 | H29: 500 | I29: =3000*Routing_Anteil_komplex -> 900 | J29: Nein | K29: =(D29*INDEX(Preise!$B$5:$B$17,MATCH(C29,Preise!$A$5:$A$17,0))+E29*INDEX(Preise!$D$5:$D$17,MATCH(C29,Preise!$A$5:$A$17,0))+F29*INDEX(Preise!$E$5:$E$17,MATCH(C29,Preise!$A$5:$A$17,0))+G29*INDEX(Preise!$F$5:$F$17,MATCH(C29,Preise!$A$5:$A$17,0))+H29*INDEX(Preise!$C$5:$C$17,MATCH(C29,Preise!$A$5:$A$17,0)))/1000000*IF(J29="Ja",Batchfaktor,1) -> 0.01 | L29: =K29*I29 -> 9 | M29: =L29/USD_je_EUR -> 7.826087
A30: 8 | B30: Routing: 70 % einfache Fälle | C30: Claude Haiku 5.5 | D30: 2500 | E30: 0 | F30: 0 | G30: 0 | H30: 500 | I30: =3000*(1-Routing_Anteil_komplex) -> 2100 | J30: Nein | K30: =(D30*INDEX(Preise!$B$5:$B$17,MATCH(C30,Preise!$A$5:$A$17,0))+E30*INDEX(Preise!$D$5:$D$17,MATCH(C30,Preise!$A$5:$A$17,0))+F30*INDEX(Preise!$E$5:$E$17,MATCH(C30,Preise!$A$5:$A$17,0))+G30*INDEX(Preise!$F$5:$F$17,MATCH(C30,Preise!$A$5:$A$17,0))+H30*INDEX(Preise!$C$5:$C$17,MATCH(C30,Preise!$A$5:$A$17,0)))/1000000*IF(J30="Ja",Batchfaktor,1) -> 0.0005 | L30: =K30*I30 -> 1.05 | M30: =L30/USD_je_EUR -> 0.91304348
B31: Summe Routing | L31: =SUM(L28:L30) -> 10.875 | M31: =SUM(M28:M30) -> 9.4565217 | N31: Tokenkosten der Routing-Variante. Nacharbeit siehe Block unten.
A33: Beispiel 8, Gesamtsystem: Was kostet Nacharbeit?
B34: Fälle mit kleinem Modell je Monat | C34: =3000*(1-Routing_Anteil_komplex) -> 2100
B35: Zusätzliche Nacharbeitsquote gegenüber mittlerem Modell | C35: 0.1
B36: Minuten Nacharbeit je betroffenem Fall | C36: 1
B37: Kosten Nacharbeit je Monat (EUR) | C37: =C34*C35*C36/60*Stundensatz -> 157.5
B38: Tokenersparnis Routing gegenüber mittlerem Modell (EUR) | C38: =M26-M31 -> 16.630435
B39: Netto-Effekt des Routings (EUR je Monat) | C39: =C38-C37 -> -140.86957 | D39: Negativ = Routing spart Tokens, kostet aber mehr Arbeitszeit, als es spart.
A41: Kennzahlen aus dem Text (Kapitel 3)
B42: RB 1: Anteil Output an den Kosten | C42: =H5*INDEX(Preise!$C$5:$C$17,MATCH(C5,Preise!$A$5:$A$17,0))/1000000/K5 -> 0.625
B43: RB 2: Faktor ausführlich / kurz | C43: =K9/K8 -> 2.7142857
B44: RB 2: Anteil Output, kurze Antwort | C44: =H8*INDEX(Preise!$C$5:$C$17,MATCH(C8,Preise!$A$5:$A$17,0))/1000000/K8 -> 0.42857143
B45: RB 2: Anteil Output, ausführliche Antwort | C45: =H9*INDEX(Preise!$C$5:$C$17,MATCH(C9,Preise!$A$5:$A$17,0))/1000000/K9 -> 0.78947368
B46: RB 3: Mehr-Input | C46: =D11/D10-1 -> 0.02020202
B47: RB 3: Mehrkosten | C47: =K11/K10-1 -> 4.0961538
B48: RB 4: Senkung Listenpreis Input | C48: =1-INDEX(Preise!$B$5:$B$17,MATCH(C13,Preise!$A$5:$A$17,0))/INDEX(Preise!$B$5:$B$17,MATCH(C12,Preise!$A$5:$A$17,0)) -> 0.33333333
B49: RB 4: tatsächliche Kostensenkung | C49: =1-K13/K12 -> 0.13279133
B50: RB 5: Einsparung 1-h-Cache gegenüber ohne Cache | C50: =1-L18/L14 -> 0.81449045
B51: RB 6: Ersparnis Batch, kleines Modell (EUR/Monat) | C51: =M20-M21 -> 0.47826087
B52: RB 6: Ersparnis Batch, mittleres Modell (EUR/Monat) | C52: =M22-M23 -> 9.5652174
B53: RB 7: Faktor Tabelle im Prompt / Code | C53: =K24/K25 -> 72.5
B54: RB 8: Nacharbeit, bei der Routing sich gerade trägt (Minuten/Monat) | C54: =C38/Stundensatz*60 -> 22.173913
B55: RB 8: dasselbe je einfachem Fall (Sekunden) | C55: =C38/Stundensatz*3600/C34 -> 0.63354037
B56: RB 1 automatisiert mit Denk-Tokens laut Parameter (USD/Monat) | C56: =L7+Denk_Tokens_Szenario*INDEX(Preise!$C$5:$C$17,MATCH(C7,Preise!$A$5:$A$17,0))/1000000*I7 -> 688.8
B57: RB 8 alles mit Opus mit Denk-Tokens laut Parameter (USD/Monat) | C57: =L27+Denk_Tokens_Szenario*INDEX(Preise!$C$5:$C$17,MATCH(C27,Preise!$A$5:$A$17,0))/1000000*I27 -> 120
B58: RB 5: Kosten eines zusätzlichen 1-h-Schreibvorgangs statt Treffer (USD) | C58: =F16*(INDEX(Preise!$E$5:$E$17,MATCH(C5,Preise!$A$5:$A$17,0))-INDEX(Preise!$F$5:$F$17,MATCH(C5,Preise!$A$5:$A$17,0)))/1000000 -> 0.1755
B59: RB 5: Mehrkosten bei einem zusätzlichen Schreibvorgang je Arbeitstag (USD/Monat) | C59: =C58*Arbeitstage -> 3.6855

Sheet Bezugsmodelle
A1: Kapitel 4: Platz-Abo, API oder lokales Modell?
A2: Vergleich nur für dieselbe Aufgabe: interaktive Arbeit einer Person mit einem Chat. Ein Platz-Abo enthält Oberfläche und Verwaltung; die API-Variante braucht eine eigene Oberfläche, deren Betreuung unten getrennt bewertet wird. Nutzungsgrenzen der Abos sind nicht in Tokens beziffert. Cache-Anteil: Anteil des Inputs, der aus dem Zwischenspeicher gelesen wird (wiederholter Gesprächsverlauf, gleiche Dokumente); der Rest wird neu in den Cache geschrieben (5 min).
A4: Nutzungsprofil | B4: Anfragen je Arbeitstag | C4: Input je Anfrage (Tokens) | D4: Output je Anfrage (Tokens) | E4: Cache-Anteil Input | F4: Modell | G4: API ohne Cache (USD/Monat) | H4: API mit Cache (USD/Monat) | I4: API mit Cache (EUR/Monat) | J4: Platzpreis jährl. (USD) | K4: Platz günstiger ab … Anfragen je Tag (mit Cache) | L4: Platz günstiger ab … (ohne Cache) | M4: Bemerkung | N4: API, halber Cache-Anteil (USD/Monat) | O4: API mit Cache und Denk-Tokens laut Parameter (USD/Monat)
A5: P1 gelegentlich | B5: 5 | C5: 3000 | D5: 600 | E5: 0 | F5: Claude Sonnet 5.5 | G5: =B5*Arbeitstage*(C5*INDEX(Preise!$B$5:$B$17,MATCH(F5,Preise!$A$5:$A$17,0))+D5*INDEX(Preise!$C$5:$C$17,MATCH(F5,Preise!$A$5:$A$17,0)))/1000000 -> 1.26 | H5: =B5*Arbeitstage*(IF(E5=0,C5*INDEX(Preise!$B$5:$B$17,MATCH(F5,Preise!$A$5:$A$17,0)),C5*(E5*INDEX(Preise!$F$5:$F$17,MATCH(F5,Preise!$A$5:$A$17,0))+(1-E5)*INDEX(Preise!$D$5:$D$17,MATCH(F5,Preise!$A$5:$A$17,0))))+D5*INDEX(Preise!$C$5:$C$17,MATCH(F5,Preise!$A$5:$A$17,0)))/1000000 -> 1.26 | I5: =H5/USD_je_EUR -> 1.0956522 | J5: =Abo_Claude_Team -> 20 | K5: =ROUNDUP(J5/((IF(E5=0,C5*INDEX(Preise!$B$5:$B$17,MATCH(F5,Preise!$A$5:$A$17,0)),C5*(E5*INDEX(Preise!$F$5:$F$17,MATCH(F5,Preise!$A$5:$A$17,0))+(1-E5)*INDEX(Preise!$D$5:$D$17,MATCH(F5,Preise!$A$5:$A$17,0))))+D5*INDEX(Preise!$C$5:$C$17,MATCH(F5,Preise!$A$5:$A$17,0)))/1000000)/Arbeitstage,0) -> 80 | L5: =ROUNDUP(J5/((C5*INDEX(Preise!$B$5:$B$17,MATCH(F5,Preise!$A$5:$A$17,0))+D5*INDEX(Preise!$C$5:$C$17,MATCH(F5,Preise!$A$5:$A$17,0)))/1000000)/Arbeitstage,0) -> 80 | M5: einzelne kurze Fragen, kaum Wiederholung | N5: =B5*Arbeitstage*(IF(E5=0,C5*INDEX(Preise!$B$5:$B$17,MATCH(F5,Preise!$A$5:$A$17,0)),C5*(E5/2*INDEX(Preise!$F$5:$F$17,MATCH(F5,Preise!$A$5:$A$17,0))+(1-E5/2)*INDEX(Preise!$D$5:$D$17,MATCH(F5,Preise!$A$5:$A$17,0))))+D5*INDEX(Preise!$C$5:$C$17,MATCH(F5,Preise!$A$5:$A$17,0)))/1000000 -> 1.26 | O5: =H5+B5*Arbeitstage*Denk_Tokens_Szenario*INDEX(Preise!$C$5:$C$17,MATCH(F5,Preise!$A$5:$A$17,0))/1000000 -> 2.31
A6: P2 regelmäßig | B6: 20 | C6: 6000 | D6: 800 | E6: 0.5 | F6: Claude Sonnet 5.5 | G6: =B6*Arbeitstage*(C6*INDEX(Preise!$B$5:$B$17,MATCH(F6,Preise!$A$5:$A$17,0))+D6*INDEX(Preise!$C$5:$C$17,MATCH(F6,Preise!$A$5:$A$17,0)))/1000000 -> 8.4 | H6: =B6*Arbeitstage*(IF(E6=0,C6*INDEX(Preise!$B$5:$B$17,MATCH(F6,Preise!$A$5:$A$17,0)),C6*(E6*INDEX(Preise!$F$5:$F$17,MATCH(F6,Preise!$A$5:$A$17,0))+(1-E6)*INDEX(Preise!$D$5:$D$17,MATCH(F6,Preise!$A$5:$A$17,0))))+D6*INDEX(Preise!$C$5:$C$17,MATCH(F6,Preise!$A$5:$A$17,0)))/1000000 -> 6.636 | I6: =H6/USD_je_EUR -> 5.7704348 | J6: =Abo_Claude_Team -> 20 | K6: =ROUNDUP(J6/((IF(E6=0,C6*INDEX(Preise!$B$5:$B$17,MATCH(F6,Preise!$A$5:$A$17,0)),C6*(E6*INDEX(Preise!$F$5:$F$17,MATCH(F6,Preise!$A$5:$A$17,0))+(1-E6)*INDEX(Preise!$D$5:$D$17,MATCH(F6,Preise!$A$5:$A$17,0))))+D6*INDEX(Preise!$C$5:$C$17,MATCH(F6,Preise!$A$5:$A$17,0)))/1000000)/Arbeitstage,0) -> 61 | L6: =ROUNDUP(J6/((C6*INDEX(Preise!$B$5:$B$17,MATCH(F6,Preise!$A$5:$A$17,0))+D6*INDEX(Preise!$C$5:$C$17,MATCH(F6,Preise!$A$5:$A$17,0)))/1000000)/Arbeitstage,0) -> 48 | M6: tägliche Arbeit mit kurzen Dokumenten | N6: =B6*Arbeitstage*(IF(E6=0,C6*INDEX(Preise!$B$5:$B$17,MATCH(F6,Preise!$A$5:$A$17,0)),C6*(E6/2*INDEX(Preise!$F$5:$F$17,MATCH(F6,Preise!$A$5:$A$17,0))+(1-E6/2)*INDEX(Preise!$D$5:$D$17,MATCH(F6,Preise!$A$5:$A$17,0))))+D6*INDEX(Preise!$C$5:$C$17,MATCH(F6,Preise!$A$5:$A$17,0)))/1000000 -> 8.148 | O6: =H6+B6*Arbeitstage*Denk_Tokens_Szenario*INDEX(Preise!$C$5:$C$17,MATCH(F6,Preise!$A$5:$A$17,0))/1000000 -> 10.836
A7: P3 intensiv mit Dokumenten | B7: 60 | C7: 15000 | D7: 1200 | E7: 0.8 | F7: Claude Sonnet 5.5 | G7: =B7*Arbeitstage*(C7*INDEX(Preise!$B$5:$B$17,MATCH(F7,Preise!$A$5:$A$17,0))+D7*INDEX(Preise!$C$5:$C$17,MATCH(F7,Preise!$A$5:$A$17,0)))/1000000 -> 52.92 | H7: =B7*Arbeitstage*(IF(E7=0,C7*INDEX(Preise!$B$5:$B$17,MATCH(F7,Preise!$A$5:$A$17,0)),C7*(E7*INDEX(Preise!$F$5:$F$17,MATCH(F7,Preise!$A$5:$A$17,0))+(1-E7)*INDEX(Preise!$D$5:$D$17,MATCH(F7,Preise!$A$5:$A$17,0))))+D7*INDEX(Preise!$C$5:$C$17,MATCH(F7,Preise!$A$5:$A$17,0)))/1000000 -> 26.082 | I7: =H7/USD_je_EUR -> 22.68 | J7: =Abo_Claude_Team -> 20 | K7: =ROUNDUP(J7/((IF(E7=0,C7*INDEX(Preise!$B$5:$B$17,MATCH(F7,Preise!$A$5:$A$17,0)),C7*(E7*INDEX(Preise!$F$5:$F$17,MATCH(F7,Preise!$A$5:$A$17,0))+(1-E7)*INDEX(Preise!$D$5:$D$17,MATCH(F7,Preise!$A$5:$A$17,0))))+D7*INDEX(Preise!$C$5:$C$17,MATCH(F7,Preise!$A$5:$A$17,0)))/1000000)/Arbeitstage,0) -> 47 | L7: =ROUNDUP(J7/((C7*INDEX(Preise!$B$5:$B$17,MATCH(F7,Preise!$A$5:$A$17,0))+D7*INDEX(Preise!$C$5:$C$17,MATCH(F7,Preise!$A$5:$A$17,0)))/1000000)/Arbeitstage,0) -> 23 | M7: Analysen, lange Gesprächsverläufe | N7: =B7*Arbeitstage*(IF(E7=0,C7*INDEX(Preise!$B$5:$B$17,MATCH(F7,Preise!$A$5:$A$17,0)),C7*(E7/2*INDEX(Preise!$F$5:$F$17,MATCH(F7,Preise!$A$5:$A$17,0))+(1-E7/2)*INDEX(Preise!$D$5:$D$17,MATCH(F7,Preise!$A$5:$A$17,0))))+D7*INDEX(Preise!$C$5:$C$17,MATCH(F7,Preise!$A$5:$A$17,0)))/1000000 -> 44.226 | O7: =H7+B7*Arbeitstage*Denk_Tokens_Szenario*INDEX(Preise!$C$5:$C$17,MATCH(F7,Preise!$A$5:$A$17,0))/1000000 -> 38.682
A8: P4 Dauernutzung, lange Dokumente | B8: 100 | C8: 40000 | D8: 1500 | E8: 0.9 | F8: Claude Sonnet 5.5 | G8: =B8*Arbeitstage*(C8*INDEX(Preise!$B$5:$B$17,MATCH(F8,Preise!$A$5:$A$17,0))+D8*INDEX(Preise!$C$5:$C$17,MATCH(F8,Preise!$A$5:$A$17,0)))/1000000 -> 199.5 | H8: =B8*Arbeitstage*(IF(E8=0,C8*INDEX(Preise!$B$5:$B$17,MATCH(F8,Preise!$A$5:$A$17,0)),C8*(E8*INDEX(Preise!$F$5:$F$17,MATCH(F8,Preise!$A$5:$A$17,0))+(1-E8)*INDEX(Preise!$D$5:$D$17,MATCH(F8,Preise!$A$5:$A$17,0))))+D8*INDEX(Preise!$C$5:$C$17,MATCH(F8,Preise!$A$5:$A$17,0)))/1000000 -> 60.06 | I8: =H8/USD_je_EUR -> 52.226087 | J8: =Abo_Claude_Team -> 20 | K8: =ROUNDUP(J8/((IF(E8=0,C8*INDEX(Preise!$B$5:$B$17,MATCH(F8,Preise!$A$5:$A$17,0)),C8*(E8*INDEX(Preise!$F$5:$F$17,MATCH(F8,Preise!$A$5:$A$17,0))+(1-E8)*INDEX(Preise!$D$5:$D$17,MATCH(F8,Preise!$A$5:$A$17,0))))+D8*INDEX(Preise!$C$5:$C$17,MATCH(F8,Preise!$A$5:$A$17,0)))/1000000)/Arbeitstage,0) -> 34 | L8: =ROUNDUP(J8/((C8*INDEX(Preise!$B$5:$B$17,MATCH(F8,Preise!$A$5:$A$17,0))+D8*INDEX(Preise!$C$5:$C$17,MATCH(F8,Preise!$A$5:$A$17,0)))/1000000)/Arbeitstage,0) -> 11 | M8: dauerhaft mehrere Dokumente im Kontext; Standard-Platz reicht evtl. nicht | N8: =B8*Arbeitstage*(IF(E8=0,C8*INDEX(Preise!$B$5:$B$17,MATCH(F8,Preise!$A$5:$A$17,0)),C8*(E8/2*INDEX(Preise!$F$5:$F$17,MATCH(F8,Preise!$A$5:$A$17,0))+(1-E8/2)*INDEX(Preise!$D$5:$D$17,MATCH(F8,Preise!$A$5:$A$17,0))))+D8*INDEX(Preise!$C$5:$C$17,MATCH(F8,Preise!$A$5:$A$17,0)))/1000000 -> 150.78 | O8: =H8+B8*Arbeitstage*Denk_Tokens_Szenario*INDEX(Preise!$C$5:$C$17,MATCH(F8,Preise!$A$5:$A$17,0))/1000000 -> 81.06
A10: Team mit gemischter Nutzung
A11: Profil | B11: Personen | C11: API ohne Cache (USD) | D11: API mit Cache (USD) | E11: API halber Cache-Anteil (USD) | F11: API mit Cache und Denk-Tokens (USD)
A12: =A5 -> P1 gelegentlich | B12: 3 | C12: =B12*G5 -> 3.78 | D12: =B12*H5 -> 3.78 | E12: =B12*N5 -> 3.78 | F12: =B12*O5 -> 6.93
A13: =A6 -> P2 regelmäßig | B13: 4 | C13: =B13*G6 -> 33.6 | D13: =B13*H6 -> 26.544 | E13: =B13*N6 -> 32.592 | F13: =B13*O6 -> 43.344
A14: =A7 -> P3 intensiv mit Dokumenten | B14: 2 | C14: =B14*G7 -> 105.84 | D14: =B14*H7 -> 52.164 | E14: =B14*N7 -> 88.452 | F14: =B14*O7 -> 77.364
A15: =A8 -> P4 Dauernutzung, lange Dokumente | B15: 1 | C15: =B15*G8 -> 199.5 | D15: =B15*H8 -> 60.06 | E15: =B15*N8 -> 150.78 | F15: =B15*O8 -> 81.06
A16: Personen gesamt | B16: =SUM(B12:B15) -> 10
A17: API-Kosten Chat ohne Cache (USD) | B17: =SUM(C12:C15) -> 342.72
A18: API-Kosten Chat mit Cache (USD) | B18: =SUM(D12:D15) -> 142.548
A19: API-Kosten Chat, halber Cache-Anteil (USD) | B19: =SUM(E12:E15) -> 275.604
A20: API-Kosten Chat mit Cache und Denk-Tokens (USD) | B20: =SUM(F12:F15) -> 208.698
A21: Zusätzlicher API-Bedarf für Automatisierung (USD) | B21: 40 | C21: Annahme, z. B. mehrere Anwendungen aus Kapitel 3
A22: Betreuung einer eigenen Chat-Oberfläche (h/Monat) | B22: 2 | C22: Annahme: Updates, Benutzerverwaltung, Fragen; Einrichtung nicht enthalten
A23: Platz-Abo für alle (USD) | B23: =B16*Abo_Claude_Team -> 200
A24: Im Claude-Team-Abo enthaltenes API-Guthaben (USD) | B24: =MIN(B16*Credit_Claude_Team,Credit_Pool_Max) -> 200
A25: Nur API ohne Zwischenspeicher, eigene Oberfläche (EUR) | B25: =(B17+B21)/USD_je_EUR+B22*Stundensatz -> 422.8
A26: Nur API mit Zwischenspeicher, eigene Oberfläche (EUR) | B26: =(B18+B21)/USD_je_EUR+B22*Stundensatz -> 248.73739
A27: dasselbe ohne Betreuungskosten der Oberfläche (EUR) | B27: =(B18+B21)/USD_je_EUR -> 158.73739
A28: Nur API, halber Cache-Anteil, eigene Oberfläche (EUR) | B28: =(B19+B21)/USD_je_EUR+B22*Stundensatz -> 364.43826
A29: Nur API mit Zwischenspeicher und Denk-Tokens, eigene Oberfläche (EUR) | B29: =(B20+B21)/USD_je_EUR+B22*Stundensatz -> 306.25913
A30: Team-Plätze, Automatisierung aus enthaltenem Guthaben (EUR) | B30: =(B23+MAX(0,B21-B24))/USD_je_EUR -> 173.91304
A31: Team-Plätze mit Premium-Platz für den Dauernutzer (EUR) | B31: =(B23-Abo_Claude_Team+Abo_Claude_Team_Premium+MAX(0,B21-MIN((B16-1)*Credit_Claude_Team+Abo_Claude_Team_Premium,Credit_Pool_Max)))/USD_je_EUR -> 243.47826 | C31: Premium-Platz laut Parameter, enthält Guthaben in Höhe des Platzpreises
A32: Plätze ohne enthaltenes Guthaben, Automatisierung per API (EUR) | B32: =(B23+B21)/USD_je_EUR -> 208.69565
A33: Zahl der Gelegenheitsnutzer im Vergleich | B33: 5 | C33: Annahme
A34: Ersparnis dieser Gelegenheitsnutzer (P1) über die API statt Plätze (EUR) | B34: =B33*(Abo_Claude_Team-H5)/USD_je_EUR -> 81.478261 | C34: Vergleich mit zwei Stunden Betreuung der eigenen Oberfläche
A36: Größeres Team: Verteilung auf die Profile (Annahme)
A37: Personen im Profil P1 | B37: 12
A38: Personen im Profil P2 | B38: 8
A39: Personen im Profil P3 | B39: 4
A40: Personen im Profil P4 | B40: 1
A41: Personen gesamt, größeres Team | B41: =B37+B38+B39+B40 -> 25
A42: API-Kosten Chat mit Cache, größeres Team (USD) | B42: =B37*H5+B38*H6+B39*H7+B40*H8 -> 232.596
A43: Größeres Team: nur API mit Zwischenspeicher, eigene Oberfläche (EUR) | B43: =(B42+B21)/USD_je_EUR+B22*Stundensatz -> 327.04
A44: Größeres Team: Team-Plätze, Automatisierung aus enthaltenem Guthaben (EUR) | B44: =(B41*Abo_Claude_Team+MAX(0,B21-MIN(B41*Credit_Claude_Team,Credit_Pool_Max)))/USD_je_EUR -> 434.78261
A45: Größeres Team: Mischmodell, Plätze nur für P3 und P4, übrige über vorhandene Software (EUR) | B45: =((B39+B40)*Abo_Claude_Team+MAX(0,B21-MIN((B39+B40)*Credit_Claude_Team,Credit_Pool_Max)))/USD_je_EUR -> 86.956522 | C45: ohne Kosten der vorhandenen Software, etwa eines Microsoft-365-Plans mit Copilot Chat
A47: Lokales Open-Weight-Modell: monatliche Vollkosten
A48: Anschaffung Hardware (EUR) | B48: 5000 | C48: Größenordnung laut einer Marktübersicht (Sekundärquelle), nicht unabhängig geprüft
A49: Nutzungsdauer (Monate) | B49: 36 | C49: Annahme
A50: Durchschnittliche Leistungsaufnahme (kW) | B50: 0.15 | C50: Annahme
A51: Betriebsstunden je Arbeitstag | B51: 8 | C51: Annahme
A52: Betreuung je Monat (h) | B52: 4 | C52: Annahme: Updates, Störungen, Modellwechsel, Sicherheit
A53: Abschreibung je Monat (EUR) | B53: =B48/B49 -> 138.88889
A54: Strom je Monat (EUR) | B54: =B50*B51*Arbeitstage*Strompreis -> 7.56
A55: Betreuung je Monat (EUR) | B55: =B52*Stundensatz -> 180
A56: Lokales Modell gesamt je Monat (EUR) | B56: =B53+B54+B55 -> 326.44889 | C56: nicht direkt mit A oder B vergleichbar: kleineres Modell, keine fertige Oberfläche, Einrichtung nicht enthalten
A58: Microsoft 365 Copilot Business (setzt Microsoft-365-Lizenz voraus)
A59: Nutzer mit Copilot-Lizenz | B59: =B16 -> 10
A60: Kosten je Monat, Listenpreis Jahresabo (EUR) | B60: =B59*Abo_Copilot_Business -> 182 | C60: Copilot Chat ist in berechtigten Microsoft-365-Plänen ohne Aufpreis enthalten. Kein Break-even: anderer Leistungsumfang.

Sheet Arbeitskosten
A1: Arbeitskosten je geleistete Stunde: Beispiel aus Kapitel 5
A2: Annahmen für eine Innendienstkraft. Den Zuschlag für Arbeitgeberanteile kennt die Lohnbuchhaltung genau.
A4: Jahresbruttogehalt | B4: 42000 | C4: Annahme
A5: Zuschlag Arbeitgeberanteile und sonstige Personalkosten | B5: 0.22 | C5: Annahme; Sozialversicherung allein rund 20–21 %, mit Umlagen und Berufsgenossenschaft eher 22–25 %
A6: Wochenstunden | B6: 40 | C6: Annahme
A7: Arbeitstage im Jahr vor Abzügen (52 × 5) | B7: 260
A8: Urlaubstage | B8: 30 | C8: Annahme
A9: Feiertage an Werktagen | B9: 10 | C9: Annahme
A10: Krankheitstage | B10: 12 | C10: Annahme
A12: Geleistete Stunden im Jahr | B12: =(B7-B8-B9-B10)*B6/5 -> 1664
A13: Arbeitskosten je geleistete Stunde | B13: =B4*(1+B5)/B12 -> 30.793269

Sheet Wirtschaftlichkeit
A1: Wirtschaftlichkeitsrechnung (Kapitel 5): Beispielvorgang mit drei Volumina
A2: Alle Beträge netto. Eingaben in Blau, die einflussreichsten gelb. Arbeitskosten aus Blatt Parameter.
A4: Position | B4: geringes Volumen | C4: mittleres Volumen | D4: hohes Volumen | E4: Einheit | F4: Formel / Erläuterung
A5: KI-Kosten je Vorgang
A6: Input-Tokens je Vorgang | B6: 3000 | C6: =$B6 -> 3000 | D6: =$B6 -> 3000 | E6: Tokens | F6: ti: Annahme
A7: Output-Tokens je Vorgang (Antwort) | B7: 500 | C7: =$B7 -> 500 | D7: =$B7 -> 500 | E7: Tokens | F7: to: Annahme
A8: Denk-Tokens je Vorgang | B8: 0 | C8: =$B8 -> 0 | D8: =$B8 -> 0 | E8: Tokens | F8: dt: 0 = Denken abgeschaltet bzw. reduziert; siehe Kapitel 3
A9: Modell | B9: Claude Sonnet 5.5 | C9: =$B9 -> Claude Sonnet 5.5 | D9: =$B9 -> Claude Sonnet 5.5 | F9: M: Auswahl aus Blatt Preise
A10: KI-Kosten je Vorgang | B10: =(B6*INDEX(Preise!$B$5:$B$17,MATCH(B9,Preise!$A$5:$A$17,0))+(B7+B8)*INDEX(Preise!$C$5:$C$17,MATCH(B9,Preise!$A$5:$A$17,0)))/1000000/USD_je_EUR -> 0.0095652174 | C10: =(C6*INDEX(Preise!$B$5:$B$17,MATCH(C9,Preise!$A$5:$A$17,0))+(C7+C8)*INDEX(Preise!$C$5:$C$17,MATCH(C9,Preise!$A$5:$A$17,0)))/1000000/USD_je_EUR -> 0.0095652174 | D10: =(D6*INDEX(Preise!$B$5:$B$17,MATCH(D9,Preise!$A$5:$A$17,0))+(D7+D8)*INDEX(Preise!$C$5:$C$17,MATCH(D9,Preise!$A$5:$A$17,0)))/1000000/USD_je_EUR -> 0.0095652174 | E10: EUR | F10: k
A11: KI-Kosten je Vorgang mit Denk-Tokens laut Parameter (Empfindlichkeit) | B11: =B10+Denk_Tokens_Szenario*INDEX(Preise!$C$5:$C$17,MATCH(B9,Preise!$A$5:$A$17,0))/1000000/USD_je_EUR -> 0.01826087 | C11: =C10+Denk_Tokens_Szenario*INDEX(Preise!$C$5:$C$17,MATCH(C9,Preise!$A$5:$A$17,0))/1000000/USD_je_EUR -> 0.01826087 | D11: =D10+Denk_Tokens_Szenario*INDEX(Preise!$C$5:$C$17,MATCH(D9,Preise!$A$5:$A$17,0))/1000000/USD_je_EUR -> 0.01826087 | E11: EUR | F11: kD: k zuzüglich Denk_Tokens_Szenario zum Output-Preis des Modells
A12: Eingaben je Szenario
A13: Vorgänge je Monat | B13: 150 | C13: 600 | D13: 2500 | E13: Anzahl | F13: V: Annahme
A14: Minuten je Vorgang ohne KI | B14: 6 | C14: 6 | D14: 6 | E14: min | F14: m0: Annahme; vorher selbst messen
A15: Minuten je Vorgang mit KI (Prüfen, Freigeben) | B15: 2 | C15: 2 | D15: 2 | E15: min | F15: m1: Annahme; die menschliche Kontrolle bleibt
A16: Anteil Vorgänge mit Korrektur | B16: 0.08 | C16: 0.08 | D16: 0.08 | E16: % | F16: f: Annahme; im Pilot messen
A17: Minuten je Korrektur | B17: 5 | C17: 5 | D17: 5 | E17: min | F17: mk: Annahme
A18: Feste Software- und Plattformkosten | B18: 25 | C18: 50 | D18: 150 | E18: EUR/Monat | F18: Sw: Annahme
A19: Wartung und Kontrolle (Stichproben, Anpassungen) | B19: 2 | C19: 4 | D19: 8 | E19: h/Monat | F19: Wh: Annahme
A20: Neutest nach Modell- oder Anbieterwechsel | B20: 4 | C20: 8 | D20: 12 | E20: h/Jahr | F20: NT: Annahme
A21: Einrichtung durch Dienstleister | B21: 25 | C21: 50 | D21: 100 | E21: h | F21: Eh: Annahme; bewertet mit externem Stundensatz aus Blatt Parameter
A22: Datenschutz und Recht, einmalig (AVV-Prüfung, Verzeichnis, Information, ggf. Betriebsrat) | B22: 300 | C22: 600 | D22: 1000 | E22: EUR | F22: DS: Annahme
A23: IT-Sicherheit, einmalig (Zugänge, Rechte, Protokollierung) | B23: 200 | C23: 400 | D23: 800 | E23: EUR | F23: IT: Annahme
A24: Schulung | B24: 4 | C24: 12 | D24: 30 | E24: h gesamt | F24: Sh: Annahme
... A26: Zahlungswirksam realisierbarer Anteil der gesparten Zeit | B26: 0 | C26: 0.3 | D26: 0.5 | E26: % | F26: r: Annahme. 0 % = Zeit wird anders genutzt, keine Ausgabe sinkt. Anteil nur ansetzen, wenn Überstunden, Aushilfen oder Fremdleistungen tatsächlich wegfallen.
A27: Ergebnisse
A28: Wartung gesamt inkl. Neutest nach Modellwechseln | B28: =B19+B20/12 -> 2.3333333 | C28: =C19+C20/12 -> 4.6666667 | D28: =D19+D20/12 -> 9 | E28: h/Monat | F28: Wt = Wh + NT / 12
A29: Arbeitszeit ohne KI | B29: =B13*B14/60 -> 15 | C29: =C13*C14/60 -> 60 | D29: =D13*D14/60 -> 250 | E29: h/Monat | F29: T0 = V × m0 / 60
A30: Arbeitszeit mit KI inkl. Korrekturen und Wartung | B30: =(B13*B15+B13*B16*B17)/60+B28 -> 8.3333333 | C30: =(C13*C15+C13*C16*C17)/60+C28 -> 28.666667 | D30: =(D13*D15+D13*D16*D17)/60+D28 -> 109 | E30: h/Monat | F30: T1 = (V × m1 + V × f × mk) / 60 + Wt
A31: Frei werdende Arbeitszeit (Kapazitätsgewinn) | B31: =B29-B30 -> 6.6666667 | C31: =C29-C30 -> 31.333333 | D31: =D29-D30 -> 141 | E31: h/Monat | F31: dT = T0 − T1
A32: Kapazitätsgewinn bewertet | B32: =B31*Stundensatz -> 300 | C32: =C31*Stundensatz -> 1410 | D32: =D31*Stundensatz -> 6345 | E32: EUR/Monat | F32: KG = dT × S
A33: KI-Kosten im Monat | B33: =B13*B10 -> 1.4347826 | C33: =C13*C10 -> 5.7391304 | D33: =D13*D10 -> 23.913043 | E33: EUR/Monat | F33: KM = V × k
A34: Laufende zahlungswirksame Kosten | B34: =B33+B18 -> 26.434783 | C34: =C33+C18 -> 55.73913 | D34: =D33+D18 -> 173.91304 | E34: EUR/Monat | F34: LK = V × k + Software
A35: Kosten je Vorgang ohne KI | B35: =B14/60*Stundensatz -> 4.5 | C35: =C14/60*Stundensatz -> 4.5 | D35: =D14/60*Stundensatz -> 4.5 | E35: EUR | F35: KV0 = m0 / 60 × S
A36: Kosten je Vorgang mit KI | B36: =IF(B13>0,(B30*Stundensatz+B34)/B13,"-") -> 2.6762319 | C36: =IF(C13>0,(C30*Stundensatz+C34)/C13,"-") -> 2.2428986 | D36: =IF(D13>0,(D30*Stundensatz+D34)/D13,"-") -> 2.0315652 | E36: EUR | F36: KV1 = (T1 × S + LK) / V
A37: Nettoeffekt kalkulatorisch | B37: =B32-B34 -> 273.56522 | C37: =C32-C34 -> 1354.2609 | D37: =D32-D34 -> 6171.087 | E37: EUR/Monat | F37: NK = KG − LK
A38: Nettoeffekt zahlungswirksam | B38: =B32*B26-B34 -> -26.434783 | C38: =C32*C26-C34 -> 367.26087 | D38: =D32*D26-D34 -> 2998.587 | E38: EUR/Monat | F38: NZ = r × KG − LK
A39: Einmalkosten zahlungswirksam (extern, Datenschutz, IT-Sicherheit) | B39: =B21*Extern_Stundensatz+B22+B23 -> 3000 | C39: =C21*Extern_Stundensatz+C22+C23 -> 6000 | D39: =D21*Extern_Stundensatz+D22+D23 -> 11800 | E39: EUR | F39: EB = Eh × externer Satz + DS + IT
A40: Interne Einmalstunden bewertet (Schulung, Ist-Aufnahme, Pilot) | B40: =(B24+B25)*Stundensatz -> 540 | C40: =(C24+C25)*Stundensatz -> 1260 | D40: =(D24+D25)*Stundensatz -> 2700 | E40: EUR | F40: EI = (Sh + Ih) × S
A41: Einmalkosten gesamt | B41: =B39+B40 -> 3540 | C41: =C39+C40 -> 7260 | D41: =D39+D40 -> 14500 | E41: EUR | F41: EG = EB + EI
A42: Amortisation kalkulatorisch | B42: =IF(B37>0,B41/B37,"keine") -> 12.940242 | C42: =IF(C37>0,C41/C37,"keine") -> 5.3608578 | D42: =IF(D37>0,D41/D37,"keine") -> 2.3496671 | E42: Monate | F42: AK = EG / NK
A43: Amortisation zahlungswirksam | B43: =IF(B38>0,B39/B38,"keine") -> keine | C43: =IF(C38>0,C39/C38,"keine") -> 16.337161 | D43: =IF(D38>0,D39/D38,"keine") -> 3.9351869 | E43: Monate | F43: AZ = EB / NZ (interne Stunden sind keine Auszahlung)
A44: Ergebnis nach Betrachtungszeitraum, kalkulatorisch | B44: =Horizont*B37-B41 -> 3025.5652 | C44: =Horizont*C37-C41 -> 25242.261 | D44: =Horizont*D37-D41 -> 133606.09 | E44: EUR | F44: H24K = Horizont × NK − EG
A45: Ergebnis nach Betrachtungszeitraum, zahlungswirksam | B45: =Horizont*B38-B39 -> -3634.4348 | C45: =Horizont*C38-C39 -> 2814.2609 | D45: =Horizont*D38-D39 -> 60166.087 | E45: EUR | F45: H24Z = Horizont × NZ − EB
A46: Nettoeffekt je zusätzlichem Vorgang | B46: =((B14-B15-B16*B17)/60)*Stundensatz-B10 -> 2.6904348 | C46: =((C14-C15-C16*C17)/60)*Stundensatz-C10 -> 2.6904348 | D46: =((D14-D15-D16*D17)/60)*Stundensatz-D10 -> 2.6904348 | E46: EUR | F46: s = ((m0 − m1 − f × mk) / 60) × S − k
A47: Break-even-Volumen kalkulatorisch (aufgerundet) | B47: =IF(B46>0,ROUNDUP((B28*Stundensatz+B18)/B46,0),"nie") -> 49 | C47: =IF(C46>0,ROUNDUP((C28*Stundensatz+C18)/C46,0),"nie") -> 97 | D47: =IF(D46>0,ROUNDUP((D28*Stundensatz+D18)/D46,0),"nie") -> 207 | E47: Vorgänge/Monat | F47: BE = (Wt × S + Sw) / s, aufgerundet
A48: Empfindlichkeit
A49: Nettoeffekt kalkulatorisch mit Arbeitskosten aus Blatt Arbeitskosten | B49: =B31*Stundensatz_KMU-B34 -> 178.85368 | C49: =C31*Stundensatz_KMU-C34 -> 909.11664 | D49: =D31*Stundensatz_KMU-D34 -> 4167.9379 | E49: EUR/Monat | F49: NK2 = dT × S_KMU − LK
A50: Amortisation kalkulatorisch mit diesen Arbeitskosten | B50: =IF(B49>0,(B39+(B24+B25)*Stundensatz_KMU)/B49,"keine") -> 18.83953 | C50: =IF(C49>0,(C39+(C24+C25)*Stundensatz_KMU)/C49,"keine") -> 7.5482191 | D50: =IF(D49>0,(D39+(D24+D25)*Stundensatz_KMU)/D49,"keine") -> 3.274424 | E50: Monate | F50: AK2
A51: Ergebnis nach Betrachtungszeitraum, kalkulatorisch mit diesen Arbeitskosten | B51: =Horizont*B49-(B39+(B24+B25)*Stundensatz_KMU) -> 922.96906 | C51: =Horizont*C49-(C39+(C24+C25)*Stundensatz_KMU) -> 14956.588 | D51: =Horizont*D49-(D39+(D24+D25)*Stundensatz_KMU) -> 86382.914 | E51: EUR | F51: H24K2 = Horizont × NK2 − (EB + (Sh + Ih) × S_KMU)
A52: Nettoeffekt kalkulatorisch bei halber Zeitersparnis | B52: =(B29-((B13*(B14+B15)/2+B13*B16*B17)/60+B28))*Stundensatz-B34 -> 48.565217 | C52: =(C29-((C13*(C14+C15)/2+C13*C16*C17)/60+C28))*Stundensatz-C34 -> 454.26087 | D52: =(D29-((D13*(D14+D15)/2+D13*D16*D17)/60+D28))*Stundensatz-D34 -> 2421.087 | E52: EUR/Monat | F52: NKh = m1 auf die Mitte zwischen m0 und m1 gesetzt
A53: Amortisation kalkulatorisch bei halber Zeitersparnis | B53: =IF(B52>0,B41/B52,"keine") -> 72.891674 | C53: =IF(C52>0,C41/C52,"keine") -> 15.982006 | D53: =IF(D52>0,D41/D52,"keine") -> 5.9890455 | E53: Monate | F53: AKh
A54: Nettoeffekt kalkulatorisch bei doppelter Korrekturquote | B54: =(B29-((B13*B15+B13*2*B16*B17)/60+B28))*Stundensatz-B34 -> 228.56522 | C54: =(C29-((C13*C15+C13*2*C16*C17)/60+C28))*Stundensatz-C34 -> 1174.2609 | D54: =(D29-((D13*D15+D13*2*D16*D17)/60+D28))*Stundensatz-D34 -> 5421.087 | E54: EUR/Monat | F54: NKf = f × 2
A55: Nettoeffekt kalkulatorisch bei höheren KI-Preisen und schwächerem Euro | B55: =B32-(B33*Preisfaktor_Szenario*USD_je_EUR/USD_je_EUR_Szenario+B18) -> 272.64286 | C55: =C32-(C33*Preisfaktor_Szenario*USD_je_EUR/USD_je_EUR_Szenario+C18) -> 1350.5714 | D55: =D32-(D33*Preisfaktor_Szenario*USD_je_EUR/USD_je_EUR_Szenario+D18) -> 6155.7143 | E55: EUR/Monat | F55: NKp = KI-Kosten × Faktor, umgerechnet zum Szenariokurs
A56: Nettoeffekt kalkulatorisch mit Denk-Tokens laut Parameter | B56: =B37-B13*(B11-B10) -> 272.26087 | C56: =C37-C13*(C11-C10) -> 1349.0435 | D56: =D37-D13*(D11-D10) -> 6149.3478 | E56: EUR/Monat | F56: NKd = NK − V × (kD − k)
A57: Nettoeffekt kalkulatorisch, Wartung und Neutest durch Dienstleister | B57: =B37-B28*(Extern_Stundensatz-Stundensatz) -> 145.23188 | C57: =C37-C28*(Extern_Stundensatz-Stundensatz) -> 1097.5942 | D57: =D37-D28*(Extern_Stundensatz-Stundensatz) -> 5676.087 | E57: EUR/Monat | F57: NKx = Wartungsstunden mit externem statt internem Satz
A58: Amortisation kalkulatorisch, Wartung durch Dienstleister | B58: =IF(B57>0,B41/B57,"keine") -> 24.374813 | C58: =IF(C57>0,C41/C57,"keine") -> 6.6144664 | D58: =IF(D57>0,D41/D57,"keine") -> 2.5545768 | E58: Monate | F58: AKx
A59: Mindestvolumen für kalkulatorische Amortisation im Betrachtungszeitraum | B59: =IF(B46>0,ROUNDUP((B41/Horizont+B28*Stundensatz+B18)/B46,0),"nie") -> 104 | C59: =IF(C46>0,ROUNDUP((C41/Horizont+C28*Stundensatz+C18)/C46,0),"nie") -> 210 | D59: =IF(D46>0,ROUNDUP((D41/Horizont+D28*Stundensatz+D18)/D46,0),"nie") -> 431 | E59: Vorgänge/Monat | F59: V24 = (EG / Horizont + Wt × S + Sw) / s, aufgerundet; übrige Annahmen der Spalte

Sheet Sensitivität
A1: Sensitivität: kalkulatorischer Nettoeffekt je Monat (EUR)
A2: Basis: übrige Annahmen der Spalte mittleres Volumen im Blatt Wirtschaftlichkeit. Zeilen: Vorgänge je Monat. Spalten: Zeitersparnis je Vorgang vor Korrekturen (m0 − m1) in Minuten.
A4: Vorgänge \ Minuten gespart | B4: 0.5 | C4: 1 | D4: 2 | E4: 3 | F4: 4 | G4: 6
A5: 50 | B5: =$A5*(((B$4-Wirtschaftlichkeit!$C$16*Wirtschaftlichkeit!$C$17)/60)*Stundensatz-Wirtschaftlichkeit!$C$10)-Wirtschaftlichkeit!$C$28*Stundensatz-Wirtschaftlichkeit!$C$18 -> -256.72826 | C5: =$A5*(((C$4-Wirtschaftlichkeit!$C$16*Wirtschaftlichkeit!$C$17)/60)*Stundensatz-Wirtschaftlichkeit!$C$10)-Wirtschaftlichkeit!$C$28*Stundensatz-Wirtschaftlichkeit!$C$18 -> -237.97826 | D5: =$A5*(((D$4-Wirtschaftlichkeit!$C$16*Wirtschaftlichkeit!$C$17)/60)*Stundensatz-Wirtschaftlichkeit!$C$10)-Wirtschaftlichkeit!$C$28*Stundensatz-Wirtschaftlichkeit!$C$18 -> -200.47826 | E5: =$A5*(((E$4-Wirtschaftlichkeit!$C$16*Wirtschaftlichkeit!$C$17)/60)*Stundensatz-Wirtschaftlichkeit!$C$10)-Wirtschaftlichkeit!$C$28*Stundensatz-Wirtschaftlichkeit!$C$18 -> -162.97826 | F5: =$A5*(((F$4-Wirtschaftlichkeit!$C$16*Wirtschaftlichkeit!$C$17)/60)*Stundensatz-Wirtschaftlichkeit!$C$10)-Wirtschaftlichkeit!$C$28*Stundensatz-Wirtschaftlichkeit!$C$18 -> -125.47826 | G5: =$A5*(((G$4-Wirtschaftlichkeit!$C$16*Wirtschaftlichkeit!$C$17)/60)*Stundensatz-Wirtschaftlichkeit!$C$10)-Wirtschaftlichkeit!$C$28*Stundensatz-Wirtschaftlichkeit!$C$18 -> -50.478261
A6: 100 | B6: =$A6*(((B$4-Wirtschaftlichkeit!$C$16*Wirtschaftlichkeit!$C$17)/60)*Stundensatz-Wirtschaftlichkeit!$C$10)-Wirtschaftlichkeit!$C$28*Stundensatz-Wirtschaftlichkeit!$C$18 -> -253.45652 | C6: =$A6*(((C$4-Wirtschaftlichkeit!$C$16*Wirtschaftlichkeit!$C$17)/60)*Stundensatz-Wirtschaftlichkeit!$C$10)-Wirtschaftlichkeit!$C$28*Stundensatz-Wirtschaftlichkeit!$C$18 -> -215.95652 | D6: =$A6*(((D$4-Wirtschaftlichkeit!$C$16*Wirtschaftlichkeit!$C$17)/60)*Stundensatz-Wirtschaftlichkeit!$C$10)-Wirtschaftlichkeit!$C$28*Stundensatz-Wirtschaftlichkeit!$C$18 -> -140.95652 | E6: =$A6*(((E$4-Wirtschaftlichkeit!$C$16*Wirtschaftlichkeit!$C$17)/60)*Stundensatz-Wirtschaftlichkeit!$C$10)-Wirtschaftlichkeit!$C$28*Stundensatz-Wirtschaftlichkeit!$C$18 -> -65.956522 | F6: =$A6*(((F$4-Wirtschaftlichkeit!$C$16*Wirtschaftlichkeit!$C$17)/60)*Stundensatz-Wirtschaftlichkeit!$C$10)-Wirtschaftlichkeit!$C$28*Stundensatz-Wirtschaftlichkeit!$C$18 -> 9.0434783 | G6: =$A6*(((G$4-Wirtschaftlichkeit!$C$16*Wirtschaftlichkeit!$C$17)/60)*Stundensatz-Wirtschaftlichkeit!$C$10)-Wirtschaftlichkeit!$C$28*Stundensatz-Wirtschaftlichkeit!$C$18 -> 159.04348
A7: 250 | B7: =$A7*(((B$4-Wirtschaftlichkeit!$C$16*Wirtschaftlichkeit!$C$17)/60)*Stundensatz-Wirtschaftlichkeit!$C$10)-Wirtschaftlichkeit!$C$28*Stundensatz-Wirtschaftlichkeit!$C$18 -> -243.6413 | C7: =$A7*(((C$4-Wirtschaftlichkeit!$C$16*Wirtschaftlichkeit!$C$17)/60)*Stundensatz-Wirtschaftlichkeit!$C$10)-Wirtschaftlichkeit!$C$28*Stundensatz-Wirtschaftlichkeit!$C$18 -> -149.8913 | D7: =$A7*(((D$4-Wirtschaftlichkeit!$C$16*Wirtschaftlichkeit!$C$17)/60)*Stundensatz-Wirtschaftlichkeit!$C$10)-Wirtschaftlichkeit!$C$28*Stundensatz-Wirtschaftlichkeit!$C$18 -> 37.608696 | E7: =$A7*(((E$4-Wirtschaftlichkeit!$C$16*Wirtschaftlichkeit!$C$17)/60)*Stundensatz-Wirtschaftlichkeit!$C$10)-Wirtschaftlichkeit!$C$28*Stundensatz-Wirtschaftlichkeit!$C$18 -> 225.1087 | F7: =$A7*(((F$4-Wirtschaftlichkeit!$C$16*Wirtschaftlichkeit!$C$17)/60)*Stundensatz-Wirtschaftlichkeit!$C$10)-Wirtschaftlichkeit!$C$28*Stundensatz-Wirtschaftlichkeit!$C$18 -> 412.6087 | G7: =$A7*(((G$4-Wirtschaftlichkeit!$C$16*Wirtschaftlichkeit!$C$17)/60)*Stundensatz-Wirtschaftlichkeit!$C$10)-Wirtschaftlichkeit!$C$28*Stundensatz-Wirtschaftlichkeit!$C$18 -> 787.6087
A8: 500 | B8: =$A8*(((B$4-Wirtschaftlichkeit!$C$16*Wirtschaftlichkeit!$C$17)/60)*Stundensatz-Wirtschaftlichkeit!$C$10)-Wirtschaftlichkeit!$C$28*Stundensatz-Wirtschaftlichkeit!$C$18 -> -227.28261 | C8: =$A8*(((C$4-Wirtschaftlichkeit!$C$16*Wirtschaftlichkeit!$C$17)/60)*Stundensatz-Wirtschaftlichkeit!$C$10)-Wirtschaftlichkeit!$C$28*Stundensatz-Wirtschaftlichkeit!$C$18 -> -39.782609 | D8: =$A8*(((D$4-Wirtschaftlichkeit!$C$16*Wirtschaftlichkeit!$C$17)/60)*Stundensatz-Wirtschaftlichkeit!$C$10)-Wirtschaftlichkeit!$C$28*Stundensatz-Wirtschaftlichkeit!$C$18 -> 335.21739 | E8: =$A8*(((E$4-Wirtschaftlichkeit!$C$16*Wirtschaftlichkeit!$C$17)/60)*Stundensatz-Wirtschaftlichkeit!$C$10)-Wirtschaftlichkeit!$C$28*Stundensatz-Wirtschaftlichkeit!$C$18 -> 710.21739 | F8: =$A8*(((F$4-Wirtschaftlichkeit!$C$16*Wirtschaftlichkeit!$C$17)/60)*Stundensatz-Wirtschaftlichkeit!$C$10)-Wirtschaftlichkeit!$C$28*Stundensatz-Wirtschaftlichkeit!$C$18 -> 1085.2174 | G8: =$A8*(((G$4-Wirtschaftlichkeit!$C$16*Wirtschaftlichkeit!$C$17)/60)*Stundensatz-Wirtschaftlichkeit!$C$10)-Wirtschaftlichkeit!$C$28*Stundensatz-Wirtschaftlichkeit!$C$18 -> 1835.2174
A9: 1000 | B9: =$A9*(((B$4-Wirtschaftlichkeit!$C$16*Wirtschaftlichkeit!$C$17)/60)*Stundensatz-Wirtschaftlichkeit!$C$10)-Wirtschaftlichkeit!$C$28*Stundensatz-Wirtschaftlichkeit!$C$18 -> -194.56522 | C9: =$A9*(((C$4-Wirtschaftlichkeit!$C$16*Wirtschaftlichkeit!$C$17)/60)*Stundensatz-Wirtschaftlichkeit!$C$10)-Wirtschaftlichkeit!$C$28*Stundensatz-Wirtschaftlichkeit!$C$18 -> 180.43478 | D9: =$A9*(((D$4-Wirtschaftlichkeit!$C$16*Wirtschaftlichkeit!$C$17)/60)*Stundensatz-Wirtschaftlichkeit!$C$10)-Wirtschaftlichkeit!$C$28*Stundensatz-Wirtschaftlichkeit!$C$18 -> 930.43478 | E9: =$A9*(((E$4-Wirtschaftlichkeit!$C$16*Wirtschaftlichkeit!$C$17)/60)*Stundensatz-Wirtschaftlichkeit!$C$10)-Wirtschaftlichkeit!$C$28*Stundensatz-Wirtschaftlichkeit!$C$18 -> 1680.4348 | F9: =$A9*(((F$4-Wirtschaftlichkeit!$C$16*Wirtschaftlichkeit!$C$17)/60)*Stundensatz-Wirtschaftlichkeit!$C$10)-Wirtschaftlichkeit!$C$28*Stundensatz-Wirtschaftlichkeit!$C$18 -> 2430.4348 | G9: =$A9*(((G$4-Wirtschaftlichkeit!$C$16*Wirtschaftlichkeit!$C$17)/60)*Stundensatz-Wirtschaftlichkeit!$C$10)-Wirtschaftlichkeit!$C$28*Stundensatz-Wirtschaftlichkeit!$C$18 -> 3930.4348
A10: 2500 | B10: =$A10*(((B$4-Wirtschaftlichkeit!$C$16*Wirtschaftlichkeit!$C$17)/60)*Stundensatz-Wirtschaftlichkeit!$C$10)-Wirtschaftlichkeit!$C$28*Stundensatz-Wirtschaftlichkeit!$C$18 -> -96.413043 | C10: =$A10*(((C$4-Wirtschaftlichkeit!$C$16*Wirtschaftlichkeit!$C$17)/60)*Stundensatz-Wirtschaftlichkeit!$C$10)-Wirtschaftlichkeit!$C$28*Stundensatz-Wirtschaftlichkeit!$C$18 -> 841.08696 | D10: =$A10*(((D$4-Wirtschaftlichkeit!$C$16*Wirtschaftlichkeit!$C$17)/60)*Stundensatz-Wirtschaftlichkeit!$C$10)-Wirtschaftlichkeit!$C$28*Stundensatz-Wirtschaftlichkeit!$C$18 -> 2716.087 | E10: =$A10*(((E$4-Wirtschaftlichkeit!$C$16*Wirtschaftlichkeit!$C$17)/60)*Stundensatz-Wirtschaftlichkeit!$C$10)-Wirtschaftlichkeit!$C$28*Stundensatz-Wirtschaftlichkeit!$C$18 -> 4591.087 | F10: =$A10*(((F$4-Wirtschaftlichkeit!$C$16*Wirtschaftlichkeit!$C$17)/60)*Stundensatz-Wirtschaftlichkeit!$C$10)-Wirtschaftlichkeit!$C$28*Stundensatz-Wirtschaftlichkeit!$C$18 -> 6466.087 | G10: =$A10*(((G$4-Wirtschaftlichkeit!$C$16*Wirtschaftlichkeit!$C$17)/60)*Stundensatz-Wirtschaftlichkeit!$C$10)-Wirtschaftlichkeit!$C$28*Stundensatz-Wirtschaftlichkeit!$C$18 -> 10216.087
A11: 5000 | B11: =$A11*(((B$4-Wirtschaftlichkeit!$C$16*Wirtschaftlichkeit!$C$17)/60)*Stundensatz-Wirtschaftlichkeit!$C$10)-Wirtschaftlichkeit!$C$28*Stundensatz-Wirtschaftlichkeit!$C$18 -> 67.173913 | C11: =$A11*(((C$4-Wirtschaftlichkeit!$C$16*Wirtschaftlichkeit!$C$17)/60)*Stundensatz-Wirtschaftlichkeit!$C$10)-Wirtschaftlichkeit!$C$28*Stundensatz-Wirtschaftlichkeit!$C$18 -> 1942.1739 | D11: =$A11*(((D$4-Wirtschaftlichkeit!$C$16*Wirtschaftlichkeit!$C$17)/60)*Stundensatz-Wirtschaftlichkeit!$C$10)-Wirtschaftlichkeit!$C$28*Stundensatz-Wirtschaftlichkeit!$C$18 -> 5692.1739 | E11: =$A11*(((E$4-Wirtschaftlichkeit!$C$16*Wirtschaftlichkeit!$C$17)/60)*Stundensatz-Wirtschaftlichkeit!$C$10)-Wirtschaftlichkeit!$C$28*Stundensatz-Wirtschaftlichkeit!$C$18 -> 9442.1739 | F11: =$A11*(((F$4-Wirtschaftlichkeit!$C$16*Wirtschaftlichkeit!$C$17)/60)*Stundensatz-Wirtschaftlichkeit!$C$10)-Wirtschaftlichkeit!$C$28*Stundensatz-Wirtschaftlichkeit!$C$18 -> 13192.174 | G11: =$A11*(((G$4-Wirtschaftlichkeit!$C$16*Wirtschaftlichkeit!$C$17)/60)*Stundensatz-Wirtschaftlichkeit!$C$10)-Wirtschaftlichkeit!$C$28*Stundensatz-Wirtschaftlichkeit!$C$18 -> 20692.174
A13: Rote Werte: Die Lösung kostet mehr, als sie an bewerteter Arbeitszeit spart. Formel je Zelle: V × (((Minuten − f × mk) / 60) × S − k) − Wt × S − Sw.
A16: Kennzahlen aus dem Text
A17: Netto gesparte Minuten je Vorgang bei 1 Minute Ersparnis (nach Korrekturen) | H17: =1-Wirtschaftlichkeit!$C$16*Wirtschaftlichkeit!$C$17 -> 0.6
A18: Break-even-Volumen bei 1 Minute Ersparnis (aufgerundet) | H18: =ROUNDUP((Wirtschaftlichkeit!$C$28*Stundensatz+Wirtschaftlichkeit!$C$18)/(((1-Wirtschaftlichkeit!$C$16*Wirtschaftlichkeit!$C$17)/60)*Stundensatz-Wirtschaftlichkeit!$C$10),0) -> 591

Sheet Bewertungsmatrix
A1: Bewertungsmatrix (Kapitel 6): Kandidaten vergleichen
A2: Jedes Kriterium von 1 bis 5 bewerten; 5 ist immer günstig für das Unternehmen (bei Aufwand, Datenschutzrisiko, Wartung und Abhängigkeit also: niedrig). Die Matrix ordnet, sie entscheidet nicht. Danach die Rechnung im Blatt Wirtschaftlichkeit.
A4: Kriterium | B4: Leitfrage | C4: Kandidat 1 | D4: Kandidat 2 | E4: Kandidat 3 | F4: Kandidat 4
A5: Häufigkeit und Schmerz | B5: Wie oft tritt das Problem bei Ihnen auf, und wie sehr stört es?
A6: Nutzen | B6: Wie viel Zeit oder Geld steht je Monat auf dem Spiel?
A7: Aufwand | B7: Lässt sich die Lösung mit vorhandenen Werkzeugen umsetzen?
A8: Datenschutzrisiko | B8: Werden personenbezogene oder vertrauliche Daten verarbeitet?
A9: Zuverlässigkeit | B9: Wie gut erledigen aktuelle Modelle die Aufgabe, und wie leicht fallen Fehler auf?
A10: Wartung | B10: Wie oft muss die Lösung angepasst werden?
A11: Anbieterabhängigkeit | B11: Wie leicht lässt sich Modell oder Anbieter wechseln?
A12: Passt zur Betriebsgröße | B12: Funktioniert die Lösung mit Ihrem Volumen und Ihrem Personal?
A13: Summe (höchstens 40) | C13: =SUM(C5:C12) -> 0 | D13: =SUM(D5:D12) -> 0 | E13: =SUM(E5:E12) -> 0 | F13: =SUM(F5:F12) -> 0
A14: Lösung ohne KI geprüft? (ja/nein)

Sheet Fall A
A1: Praxisfall A (Kapitel 7): Montageberichte per Sprachnachricht
A2: Alle Werte sind Annahmen für ein Modellbeispiel, keine Messwerte. Monteur- und Bürozeit getrennt.
A4: Position | B4: Kleinbetrieb | C4: Mittlerer Betrieb | D4: Betrieb mit hohem Volumen | E4: Einheit | F4: Formel / Erläuterung
A5: KI-Kosten je Vorgang
A6: Audiominuten je Bericht | B6: 1.5 | C6: =$B6 -> 1.5 | D6: =$B6 -> 1.5 | E6: min | F6: am: Annahme
A7: Input-Tokens Extraktion (Anweisung, Abschrift, Baustellen-, Mitarbeiter- und Materialliste) | B7: 1500 | C7: =$B7 -> 1500 | D7: =$B7 -> 1500 | E7: Tokens | F7: ti: Annahme
A8: Output-Tokens (strukturierter Bericht) | B8: 400 | C8: =$B8 -> 400 | D8: =$B8 -> 400 | E8: Tokens | F8: to: Annahme
A9: Denk-Tokens je Bericht | B9: 0 | C9: =$B9 -> 0 | D9: =$B9 -> 0 | E9: Tokens | F9: dt: 0: vorgelagertes Denken abgeschaltet (Sonnet 5.5: thinking between_tools, ohne Werkzeuge)
A10: Modell für die Extraktion | B10: Claude Sonnet 5.5 | C10: =$B10 -> Claude Sonnet 5.5 | D10: =$B10 -> Claude Sonnet 5.5 | F10: M: Auswahl aus Blatt Preise
A11: KI-Kosten je Vorgang | B11: =(B6*Transkription_USD_min+(B7*INDEX(Preise!$B$5:$B$17,MATCH(B10,Preise!$A$5:$A$17,0))+(B8+B9)*INDEX(Preise!$C$5:$C$17,MATCH(B10,Preise!$A$5:$A$17,0)))/1000000)/USD_je_EUR -> 0.013913043 | C11: =(C6*Transkription_USD_min+(C7*INDEX(Preise!$B$5:$B$17,MATCH(C10,Preise!$A$5:$A$17,0))+(C8+C9)*INDEX(Preise!$C$5:$C$17,MATCH(C10,Preise!$A$5:$A$17,0)))/1000000)/USD_je_EUR -> 0.013913043 | D11: =(D6*Transkription_USD_min+(D7*INDEX(Preise!$B$5:$B$17,MATCH(D10,Preise!$A$5:$A$17,0))+(D8+D9)*INDEX(Preise!$C$5:$C$17,MATCH(D10,Preise!$A$5:$A$17,0)))/1000000)/USD_je_EUR -> 0.013913043 | E11: EUR | F11: k
A12: KI-Kosten je Vorgang mit Denk-Tokens laut Parameter (Empfindlichkeit) | B12: =B11+Denk_Tokens_Szenario*INDEX(Preise!$C$5:$C$17,MATCH(B10,Preise!$A$5:$A$17,0))/1000000/USD_je_EUR -> 0.022608696 | C12: =C11+Denk_Tokens_Szenario*INDEX(Preise!$C$5:$C$17,MATCH(C10,Preise!$A$5:$A$17,0))/1000000/USD_je_EUR -> 0.022608696 | D12: =D11+Denk_Tokens_Szenario*INDEX(Preise!$C$5:$C$17,MATCH(D10,Preise!$A$5:$A$17,0))/1000000/USD_je_EUR -> 0.022608696 | E12: EUR | F12: kD: k zuzüglich Denk_Tokens_Szenario zum Output-Preis des Modells
A13: Eingaben je Szenario
A14: Monteure | B14: 4 | C14: 15 | D14: 50 | E14: Personen | F14: Nm: Annahme
A15: Berichte je Monteur und Arbeitstag | B15: 1 | C15: 1 | D15: 1 | E15: Anzahl | F15: b: Annahme
A16: Berichte je Monat | B16: =B14*B15*Arbeitstage -> 84 | C16: =C14*C15*Arbeitstage -> 315 | D16: =D14*D15*Arbeitstage -> 1050 | E16: Anzahl | F16: V: Nm × b × Arbeitstage
A17: Minuten Monteur je Bericht ohne KI (Zettel schreiben) | B17: 8 | C17: 8 | D17: 8 | E17: min | F17: m0M: Annahme
A18: Minuten Büro je Bericht ohne KI (Abtippen) | B18: 6 | C18: 6 | D18: 6 | E18: min | F18: m0B: Annahme
A19: Minuten Monteur je Bericht mit KI (Sprechen) | B19: 2 | C19: 2 | D19: 2 | E19: min | F19: m1M: Annahme
A20: Minuten Büro je Bericht mit KI (Prüfen, Freigeben) | B20: 3 | C20: 3 | D20: 3 | E20: min | F20: m1B: Annahme
A21: Minuten je Bericht ohne KI gesamt | B21: =B17+B18 -> 14 | C21: =C17+C18 -> 14 | D21: =D17+D18 -> 14 | E21: min | F21: m0:
A22: Minuten je Bericht mit KI gesamt | B22: =B19+B20 -> 5 | C22: =C19+C20 -> 5 | D22: =D19+D20 -> 5 | E22: min | F22: m1:
A23: Anteil Berichte mit Rückfrage | B23: 0.1 | C23: 0.1 | D23: 0.1 | E23: % | F23: f: Annahme; im Pilot messen
A24: Minuten je Rückfrage, Monteur | B24: 5 | C24: 5 | D24: 5 | E24: min | F24: mkM: Annahme
A25: Minuten je Rückfrage, Büro | B25: 5 | C25: 5 | D25: 5 | E25: min | F25: mkB: Annahme
A26: Minuten je Rückfrage gesamt | B26: =B24+B25 -> 10 | C26: =C24+C25 -> 10 | D26: =D24+D25 -> 10 | E26: min | F26: mk: eine Rückfrage bindet zwei Personen
A27: Schulung je Monteur | B27: 0.5 | C27: 0.5 | D27: 0.5 | E27: h | F27: ShM: Annahme
A28: Schulung Büro | B28: 4 | C28: 6 | D28: 10 | E28: h | F28: ShB: Annahme
A29: Feste Software- und Plattformkosten | B29: 30 | C29: 60 | D29: 150 | E29: EUR/Monat | F29: Sw: Annahme
A30: Wartung und Kontrolle (Stichproben, Anpassungen) | B30: 2 | C30: 4 | D30: 8 | E30: h/Monat | F30: Wh: Annahme
A31: Neutest nach Modell- oder Anbieterwechsel | B31: 4 | C31: 8 | D31: 12 | E31: h/Jahr | F31: NT: Annahme
A32: Einrichtung durch Dienstleister | B32: 30 | C32: 60 | D32: 120 | E32: h | F32: Eh: Annahme; bewertet mit externem Stundensatz aus Blatt Parameter
A33: Datenschutz und Recht, einmalig (AVV-Prüfung, Verzeichnis, Information, ggf. Betriebsrat) | B33: 500 | C33: 1000 | D33: 2000 | E33: EUR | F33: DS: Annahme
A34: IT-Sicherheit, einmalig (Zugänge, Rechte, Protokollierung) | B34: 300 | C34: 500 | D34: 1000 | E34: EUR | F34: IT: Annahme
A35: Schulung | B35: =B14*B27+B28 -> 6 | C35: =C14*C27+C28 -> 13.5 | D35: =D14*D27+D28 -> 35 | E35: h gesamt | F35: Sh: Annahme
A36: Interne Stunden für Auswahl, Ist-Aufnahme, Testfälle und Pilot; bei eigener Einrichtung zusätzlich deren Stunden | B36: 10 | C36: 20 | D36: 40 | E36: h gesamt | F36: Ih: Annahme
A37: Zahlungswirksam realisierbarer Anteil der gesparten Zeit | B37: 0 | C37: 0.3 | D37: 0.5 | E37: % | F37: r: Annahme. 0 % = Zeit wird anders genutzt, keine Ausgabe sinkt. Anteil nur ansetzen, wenn Überstunden, Aushilfen oder Fremdleistungen tatsächlich wegfallen.
A38: Ergebnisse
A39: Wartung gesamt inkl. Neutest nach Modellwechseln | B39: =B30+B31/12 -> 2.3333333 | C39: =C30+C31/12 -> 4.6666667 | D39: =D30+D31/12 -> 9 | E39: h/Monat | F39: Wt = Wh + NT / 12
A40: Arbeitszeit ohne KI | B40: =B16*B21/60 -> 19.6 | C40: =C16*C21/60 -> 73.5 | D40: =D16*D21/60 -> 245 | E40: h/Monat | F40: T0 = V × m0 / 60
A41: Arbeitszeit mit KI inkl. Korrekturen und Wartung | B41: =(B16*B22+B16*B23*B26)/60+B39 -> 10.733333 | C41: =(C16*C22+C16*C23*C26)/60+C39 -> 36.166667 | D41: =(D16*D22+D16*D23*D26)/60+D39 -> 114 | E41: h/Monat | F41: T1 = (V × m1 + V × f × mk) / 60 + Wt
A42: Frei werdende Arbeitszeit (Kapazitätsgewinn) | B42: =B40-B41 -> 8.8666667 | C42: =C40-C41 -> 37.333333 | D42: =D40-D41 -> 131 | E42: h/Monat | F42: dT = T0 − T1
A43: Kapazitätsgewinn bewertet | B43: =B42*Stundensatz -> 399 | C43: =C42*Stundensatz -> 1680 | D43: =D42*Stundensatz -> 5895 | E43: EUR/Monat | F43: KG = dT × S
A44: KI-Kosten im Monat | B44: =B16*B11 -> 1.1686957 | C44: =C16*C11 -> 4.3826087 | D44: =D16*D11 -> 14.608696 | E44: EUR/Monat | F44: KM = V × k
A45: Laufende zahlungswirksame Kosten | B45: =B44+B29 -> 31.168696 | C45: =C44+C29 -> 64.382609 | D45: =D44+D29 -> 164.6087 | E45: EUR/Monat | F45: LK = V × k + Software
A46: Kosten je Vorgang ohne KI | B46: =B21/60*Stundensatz -> 10.5 | C46: =C21/60*Stundensatz -> 10.5 | D46: =D21/60*Stundensatz -> 10.5 | E46: EUR | F46: KV0 = m0 / 60 × S
A47: Kosten je Vorgang mit KI | B47: =(B41*Stundensatz+B45)/B16 -> 6.1210559 | C47: =(C41*Stundensatz+C45)/C16 -> 5.3710559 | D47: =(D41*Stundensatz+D45)/D16 -> 5.0424845 | E47: EUR | F47: KV1 = (T1 × S + LK) / V
A48: Nettoeffekt kalkulatorisch | B48: =B43-B45 -> 367.8313 | C48: =C43-C45 -> 1615.6174 | D48: =D43-D45 -> 5730.3913 | E48: EUR/Monat | F48: NK = KG − LK
A49: Nettoeffekt zahlungswirksam | B49: =B43*B37-B45 -> -31.168696 | C49: =C43*C37-C45 -> 439.61739 | D49: =D43*D37-D45 -> 2782.8913 | E49: EUR/Monat | F49: NZ = r × KG − LK
A50: Einmalkosten zahlungswirksam (extern, Datenschutz, IT-Sicherheit) | B50: =B32*Extern_Stundensatz+B33+B34 -> 3800 | C50: =C32*Extern_Stundensatz+C33+C34 -> 7500 | D50: =D32*Extern_Stundensatz+D33+D34 -> 15000 | E50: EUR | F50: EB = Eh × externer Satz + DS + IT
A51: Interne Einmalstunden bewertet (Schulung, Ist-Aufnahme, Pilot) | B51: =(B35+B36)*Stundensatz -> 720 | C51: =(C35+C36)*Stundensatz -> 1507.5 | D51: =(D35+D36)*Stundensatz -> 3375 | E51: EUR | F51: EI = (Sh + Ih) × S
A52: Einmalkosten gesamt | B52: =B50+B51 -> 4520 | C52: =C50+C51 -> 9007.5 | D52: =D50+D51 -> 18375 | E52: EUR | F52: EG = EB + EI
A53: Amortisation kalkulatorisch | B53: =IF(B48>0,B52/B48,"keine") -> 12.288242 | C53: =IF(C48>0,C52/C48,"keine") -> 5.575268 | D53: =IF(D48>0,D52/D48,"keine") -> 3.2065873 | E53: Monate | F53: AK = EG / NK
A54: Amortisation zahlungswirksam | B54: =IF(B49>0,B50/B49,"keine") -> keine | C54: =IF(C49>0,C50/C49,"keine") -> 17.06029 | D54: =IF(D49>0,D50/D49,"keine") -> 5.3900776 | E54: Monate | F54: AZ = EB / NZ (interne Stunden sind keine Auszahlung)
A55: Ergebnis nach Betrachtungszeitraum, kalkulatorisch | B55: =Horizont*B48-B52 -> 4307.9513 | C55: =Horizont*C48-C52 -> 29767.317 | D55: =Horizont*D48-D52 -> 119154.39 | E55: EUR | F55: H24K = Horizont × NK − EG
A56: Ergebnis nach Betrachtungszeitraum, zahlungswirksam | B56: =Horizont*B49-B50 -> -4548.0487 | C56: =Horizont*C49-C50 -> 3050.8174 | D56: =Horizont*D49-D50 -> 51789.391 | E56: EUR | F56: H24Z = Horizont × NZ − EB
A57: Nettoeffekt je zusätzlichem Vorgang | B57: =((B21-B22-B23*B26)/60)*Stundensatz-B11 -> 5.986087 | C57: =((C21-C22-C23*C26)/60)*Stundensatz-C11 -> 5.986087 | D57: =((D21-D22-D23*D26)/60)*Stundensatz-D11 -> 5.986087 | E57: EUR | F57: s = ((m0 − m1 − f × mk) / 60) × S − k
A58: Break-even-Volumen kalkulatorisch (aufgerundet) | B58: =IF(B57>0,ROUNDUP((B39*Stundensatz+B29)/B57,0),"nie") -> 23 | C58: =IF(C57>0,ROUNDUP((C39*Stundensatz+C29)/C57,0),"nie") -> 46 | D58: =IF(D57>0,ROUNDUP((D39*Stundensatz+D29)/D57,0),"nie") -> 93 | E58: Vorgänge/Monat | F58: BE = (Wt × S + Sw) / s, aufgerundet
A59: Empfindlichkeit
A60: Nettoeffekt kalkulatorisch mit Arbeitskosten aus Blatt Arbeitskosten | B60: =B42*Stundensatz_KMU-B45 -> 241.86496 | C60: =C42*Stundensatz_KMU-C45 -> 1085.2328 | D60: =D42*Stundensatz_KMU-D45 -> 3869.3096 | E60: EUR/Monat | F60: NK2 = dT × S_KMU − LK
A61: Amortisation kalkulatorisch mit diesen Arbeitskosten | B61: =IF(B60>0,(B50+(B35+B36)*Stundensatz_KMU)/B60,"keine") -> 17.748302 | C61: =IF(C60>0,(C50+(C35+C36)*Stundensatz_KMU)/C60,"keine") -> 7.8615157 | D61: =IF(D60>0,(D50+(D35+D36)*Stundensatz_KMU)/D60,"keine") -> 4.4735359 | E61: Monate | F61: AK2
A62: Ergebnis nach Betrachtungszeitraum, kalkulatorisch mit diesen Arbeitskosten | B62: =Horizont*B60-(B50+(B35+B36)*Stundensatz_KMU) -> 1512.0667 | C62: =Horizont*C60-(C50+(C35+C36)*Stundensatz_KMU) -> 17514.012 | D62: =Horizont*D60-(D50+(D35+D36)*Stundensatz_KMU) -> 75553.935 | E62: EUR | F62: H24K2 = Horizont × NK2 − (EB + (Sh + Ih) × S_KMU)
A63: Nettoeffekt kalkulatorisch bei halber Zeitersparnis | B63: =(B40-((B16*(B21+B22)/2+B16*B23*B26)/60+B39))*Stundensatz-B45 -> 84.331304 | C63: =(C40-((C16*(C21+C22)/2+C16*C23*C26)/60+C39))*Stundensatz-C45 -> 552.49239 | D63: =(D40-((D16*(D21+D22)/2+D16*D23*D26)/60+D39))*Stundensatz-D45 -> 2186.6413 | E63: EUR/Monat | F63: NKh = m1 auf die Mitte zwischen m0 und m1 gesetzt
A64: Amortisation kalkulatorisch bei halber Zeitersparnis | B64: =IF(B63>0,B52/B63,"keine") -> 53.598127 | C64: =IF(C63>0,C52/C63,"keine") -> 16.303392 | D64: =IF(D63>0,D52/D63,"keine") -> 8.4032987 | E64: Monate | F64: AKh
A65: Nettoeffekt kalkulatorisch bei doppelter Korrekturquote | B65: =(B40-((B16*B22+B16*2*B23*B26)/60+B39))*Stundensatz-B45 -> 304.8313 | C65: =(C40-((C16*C22+C16*2*C23*C26)/60+C39))*Stundensatz-C45 -> 1379.3674 | D65: =(D40-((D16*D22+D16*2*D23*D26)/60+D39))*Stundensatz-D45 -> 4942.8913 | E65: EUR/Monat | F65: NKf = f × 2
A66: Nettoeffekt kalkulatorisch bei höheren KI-Preisen und schwächerem Euro | B66: =B43-(B44*Preisfaktor_Szenario*USD_je_EUR/USD_je_EUR_Szenario+B29) -> 367.08 | C66: =C43-(C44*Preisfaktor_Szenario*USD_je_EUR/USD_je_EUR_Szenario+C29) -> 1612.8 | D66: =D43-(D44*Preisfaktor_Szenario*USD_je_EUR/USD_je_EUR_Szenario+D29) -> 5721 | E66: EUR/Monat | F66: NKp = KI-Kosten × Faktor, umgerechnet zum Szenariokurs
A67: Nettoeffekt kalkulatorisch mit Denk-Tokens laut Parameter | B67: =B48-B16*(B12-B11) -> 367.10087 | C67: =C48-C16*(C12-C11) -> 1612.8783 | D67: =D48-D16*(D12-D11) -> 5721.2609 | E67: EUR/Monat | F67: NKd = NK − V × (kD − k)
A68: Nettoeffekt kalkulatorisch, Wartung und Neutest durch Dienstleister | B68: =B48-B39*(Extern_Stundensatz-Stundensatz) -> 239.49797 | C68: =C48-C39*(Extern_Stundensatz-Stundensatz) -> 1358.9507 | D68: =D48-D39*(Extern_Stundensatz-Stundensatz) -> 5235.3913 | E68: EUR/Monat | F68: NKx = Wartungsstunden mit externem statt internem Satz
A69: Amortisation kalkulatorisch, Wartung durch Dienstleister | B69: =IF(B68>0,B52/B68,"keine") -> 18.872811 | C69: =IF(C68>0,C52/C68,"keine") -> 6.6282757 | D69: =IF(D68>0,D52/D68,"keine") -> 3.5097663 | E69: Monate | F69: AKx
A70: Mindestvolumen für kalkulatorische Amortisation im Betrachtungszeitraum | B70: =IF(B57>0,ROUNDUP((B52/Horizont+B39*Stundensatz+B29)/B57,0),"nie") -> 55 | C70: =IF(C57>0,ROUNDUP((C52/Horizont+C39*Stundensatz+C29)/C57,0),"nie") -> 108 | D70: =IF(D57>0,ROUNDUP((D52/Horizont+D39*Stundensatz+D29)/D57,0),"nie") -> 221 | E70: Vorgänge/Monat | F70: V24 = (EG / Horizont + Wt × S + Sw) / s, aufgerundet; übrige Annahmen der Spalte
A71: Variante: nur Bürozeit zählt
A72: Nettoeffekt kalkulatorisch, nur Bürozeit | B72: =((B16*(B18-B20-B23*B25))/60-B39)*Stundensatz-B45 -> 21.331304 | C72: =((C16*(C18-C20-C23*C25))/60-C39)*Stundensatz-C45 -> 316.24239 | D72: =((D16*(D18-D20-D23*D25))/60-D39)*Stundensatz-D45 -> 1399.1413 | E72: EUR/Monat | F72: NKB = Monteurzeit wird nicht bewertet
A73: Amortisation kalkulatorisch, nur Bürozeit | B73: =IF(B72>0,B52/B72,"keine") -> 211.89515 | C73: =IF(C72>0,C52/C72,"keine") -> 28.482899 | D73: =IF(D72>0,D52/D72,"keine") -> 13.133055 | E73: Monate | F73: AKB
A74: Break-even, nur Bürozeit (aufgerundet) | B74: =IF(((B18-B20-B23*B25)/60)*Stundensatz-B11>0,ROUNDUP((B39*Stundensatz+B29)/(((B18-B20-B23*B25)/60)*Stundensatz-B11),0),"nie") -> 73 | C74: =IF(((C18-C20-C23*C25)/60)*Stundensatz-C11>0,ROUNDUP((C39*Stundensatz+C29)/(((C18-C20-C23*C25)/60)*Stundensatz-C11),0),"nie") -> 146 | D74: =IF(((D18-D20-D23*D25)/60)*Stundensatz-D11>0,ROUNDUP((D39*Stundensatz+D29)/(((D18-D20-D23*D25)/60)*Stundensatz-D11),0),"nie") -> 299 | E74: Berichte/Monat | F74: BEB
A75: Variante: Vergleich mit gut genutztem digitalem Formular
A76: Minuten je Bericht mit digitalem Formular (Monteur plus Büro) | B76: 6 | C76: 6 | D76: 6 | E76: min | F76: m0F: Annahme: 4 min Monteur + 2 min Büro
A77: Nettoeffekt je zusätzlichem Bericht gegenüber Formular | B77: =((B76-B22-B23*B26)/60)*Stundensatz-B11 -> -0.013913043 | C77: =((C76-C22-C23*C26)/60)*Stundensatz-C11 -> -0.013913043 | D77: =((D76-D22-D23*D26)/60)*Stundensatz-D11 -> -0.013913043 | E77: EUR | F77: sF
A78: Nettoeffekt kalkulatorisch gegenüber Formular | B78: =(B16*B76/60-B41)*Stundensatz-B45 -> -136.1687 | C78: =(C16*C76/60-C41)*Stundensatz-C45 -> -274.38261 | D78: =(D16*D76/60-D41)*Stundensatz-D45 -> -569.6087 | E78: EUR/Monat | F78: NKF
A79: Zusatzeffekt: bisher nicht abgerechnete Leistungen
A80: Verrechnungssatz je Regiestunde (netto) | B80: 60 | C80: 60 | D80: 60 | E80: EUR/h | F80: VS: Annahme; eigenen Satz einsetzen
A81: Nötige zusätzlich abgerechnete Stunden je Monat für zahlungswirksame Amortisation in 12 Monaten | B81: =MAX(0,B50/12-B49)/B80 -> 5.797256 | C81: =MAX(0,C50/12-C49)/C80 -> 3.0897101 | D81: =MAX(0,D50/12-D49)/D80 -> 0 | E81: h/Monat | F81: RS = MAX(0; EB / 12 − NZ) / VS
A82: dasselbe je Monteur | B82: =B81/B14 -> 1.449314 | C82: =C81/C14 -> 0.20598068 | D82: =D81/D14 -> 0 | E82: h/Monat | F82: RSm

Sheet Fall B
A1: Praxisfall B (Kapitel 8): Auftragsbestätigungen gegen Bestellung prüfen
A2: Alle Werte sind Annahmen. Das Modell liest nur aus; der Abgleich erfolgt regelbasiert.
A4: Position | B4: Kleinbetrieb | C4: Mittlerer Betrieb | D4: Betrieb mit hohem Volumen | E4: Einheit | F4: Formel / Erläuterung
A5: KI-Kosten je Vorgang
A6: Input-Tokens je Auftragsbestätigung (Text der AB plus Anweisung) | B6: 4000 | C6: =$B6 -> 4000 | D6: =$B6 -> 4000 | E6: Tokens | F6: ti: Annahme: 2–3 Seiten Text
A7: Output-Tokens (Positionen als strukturierte Liste) | B7: 600 | C7: =$B7 -> 600 | D7: =$B7 -> 600 | E7: Tokens | F7: to: Annahme
A8: Denk-Tokens je Bestätigung | B8: 0 | C8: =$B8 -> 0 | D8: =$B8 -> 0 | E8: Tokens | F8: dt: 0: vorgelagertes Denken abgeschaltet (Sonnet 5.5: thinking between_tools, ohne Werkzeuge)
A9: Modell für die Extraktion | B9: Claude Sonnet 5.5 | C9: =$B9 -> Claude Sonnet 5.5 | D9: =$B9 -> Claude Sonnet 5.5 | F9: M: Auswahl aus Blatt Preise
A10: Batch-Verarbeitung | B10: Nein | C10: =$B10 -> Nein | D10: =$B10 -> Nein | F10: BT: Standard: sofort, weil Abweichungen zeitkritisch sind
A11: KI-Kosten je Vorgang | B11: =(B6*INDEX(Preise!$B$5:$B$17,MATCH(B9,Preise!$A$5:$A$17,0))+(B7+B8)*INDEX(Preise!$C$5:$C$17,MATCH(B9,Preise!$A$5:$A$17,0)))/1000000*IF(B10="Ja",Batchfaktor,1)/USD_je_EUR -> 0.012173913 | C11: =(C6*INDEX(Preise!$B$5:$B$17,MATCH(C9,Preise!$A$5:$A$17,0))+(C7+C8)*INDEX(Preise!$C$5:$C$17,MATCH(C9,Preise!$A$5:$A$17,0)))/1000000*IF(C10="Ja",Batchfaktor,1)/USD_je_EUR -> 0.012173913 | D11: =(D6*INDEX(Preise!$B$5:$B$17,MATCH(D9,Preise!$A$5:$A$17,0))+(D7+D8)*INDEX(Preise!$C$5:$C$17,MATCH(D9,Preise!$A$5:$A$17,0)))/1000000*IF(D10="Ja",Batchfaktor,1)/USD_je_EUR -> 0.012173913 | E11: EUR | F11: k
A12: KI-Kosten je Vorgang mit Denk-Tokens laut Parameter (Empfindlichkeit) | B12: =B11+Denk_Tokens_Szenario*INDEX(Preise!$C$5:$C$17,MATCH(B9,Preise!$A$5:$A$17,0))/1000000*IF(B10="Ja",Batchfaktor,1)/USD_je_EUR -> 0.020869565 | C12: =C11+Denk_Tokens_Szenario*INDEX(Preise!$C$5:$C$17,MATCH(C9,Preise!$A$5:$A$17,0))/1000000*IF(C10="Ja",Batchfaktor,1)/USD_je_EUR -> 0.020869565 | D12: =D11+Denk_Tokens_Szenario*INDEX(Preise!$C$5:$C$17,MATCH(D9,Preise!$A$5:$A$17,0))/1000000*IF(D10="Ja",Batchfaktor,1)/USD_je_EUR -> 0.020869565 | E12: EUR | F12: kD: k zuzüglich Denk_Tokens_Szenario zum Output-Preis des Modells
A13: Eingaben je Szenario
A14: Auftragsbestätigungen je Monat | B14: 60 | C14: 300 | D14: 1200 | E14: Anzahl | F14: V: Annahme
A15: Minuten je AB heute (oft nur flüchtige Prüfung) | B15: 3 | C15: 3 | D15: 3 | E15: min | F15: m0: Annahme für den Ist-Zustand
A16: Minuten je AB mit KI (Ergebnis ansehen, Markierungen prüfen) | B16: 1 | C16: 1 | D16: 1 | E16: min | F16: m1: Annahme
A17: Anteil Fehlalarme oder Auslesefehler | B17: 0.1 | C17: 0.1 | D17: 0.1 | E17: % | F17: f: Annahme; im Pilot messen
A18: Minuten je Fehlalarm | B18: 4 | C18: 4 | D18: 4 | E18: min | F18: mk: Annahme: AB manuell gegenprüfen
A19: Feste Software- und Plattformkosten | B19: 20 | C19: 50 | D19: 120 | E19: EUR/Monat | F19: Sw: Annahme
A20: Wartung und Kontrolle (Stichproben, Anpassungen) | B20: 2 | C20: 4 | D20: 8 | E20: h/Monat | F20: Wh: Annahme
A21: Neutest nach Modell- oder Anbieterwechsel | B21: 4 | C21: 8 | D21: 12 | E21: h/Jahr | F21: NT: Annahme
A22: Einrichtung durch Dienstleister | B22: 25 | C22: 60 | D22: 120 | E22: h | F22: Eh: Annahme; bewertet mit externem Stundensatz aus Blatt Parameter
A23: Datenschutz und Recht, einmalig (AVV-Prüfung, Verzeichnis, Information, ggf. Betriebsrat) | B23: 200 | C23: 300 | D23: 500 | E23: EUR | F23: DS: Annahme
A24: IT-Sicherheit, einmalig (Zugänge, Rechte, Protokollierung) | B24: 200 | C24: 400 | D24: 800 | E24: EUR | F24: IT: Annahme
A25: Schulung | B25: 2 | C25: 4 | D25: 8 | E25: h gesamt | F25: Sh: Annahme
... A27: Zahlungswirksam realisierbarer Anteil der gesparten Zeit | B27: 0 | C27: 0.3 | D27: 0.5 | E27: % | F27: r: Annahme. 0 % = Zeit wird anders genutzt, keine Ausgabe sinkt. Anteil nur ansetzen, wenn Überstunden, Aushilfen oder Fremdleistungen tatsächlich wegfallen.
A28: Ergebnisse
A29: Wartung gesamt inkl. Neutest nach Modellwechseln | B29: =B20+B21/12 -> 2.3333333 | C29: =C20+C21/12 -> 4.6666667 | D29: =D20+D21/12 -> 9 | E29: h/Monat | F29: Wt = Wh + NT / 12
A30: Arbeitszeit ohne KI | B30: =B14*B15/60 -> 3 | C30: =C14*C15/60 -> 15 | D30: =D14*D15/60 -> 60 | E30: h/Monat | F30: T0 = V × m0 / 60
A31: Arbeitszeit mit KI inkl. Korrekturen und Wartung | B31: =(B14*B16+B14*B17*B18)/60+B29 -> 3.7333333 | C31: =(C14*C16+C14*C17*C18)/60+C29 -> 11.666667 | D31: =(D14*D16+D14*D17*D18)/60+D29 -> 37 | E31: h/Monat | F31: T1 = (V × m1 + V × f × mk) / 60 + Wt
A32: Frei werdende Arbeitszeit (Kapazitätsgewinn) | B32: =B30-B31 -> -0.73333333 | C32: =C30-C31 -> 3.3333333 | D32: =D30-D31 -> 23 | E32: h/Monat | F32: dT = T0 − T1
A33: Kapazitätsgewinn bewertet | B33: =B32*Stundensatz -> -33 | C33: =C32*Stundensatz -> 150 | D33: =D32*Stundensatz -> 1035 | E33: EUR/Monat | F33: KG = dT × S
A34: KI-Kosten im Monat | B34: =B14*B11 -> 0.73043478 | C34: =C14*C11 -> 3.6521739 | D34: =D14*D11 -> 14.608696 | E34: EUR/Monat | F34: KM = V × k
A35: Laufende zahlungswirksame Kosten | B35: =B34+B19 -> 20.730435 | C35: =C34+C19 -> 53.652174 | D35: =D34+D19 -> 134.6087 | E35: EUR/Monat | F35: LK = V × k + Software
A36: Kosten je Vorgang ohne KI | B36: =B15/60*Stundensatz -> 2.25 | C36: =C15/60*Stundensatz -> 2.25 | D36: =D15/60*Stundensatz -> 2.25 | E36: EUR | F36: KV0 = m0 / 60 × S
A37: Kosten je Vorgang mit KI | B37: =(B31*Stundensatz+B35)/B14 -> 3.1455072 | C37: =(C31*Stundensatz+C35)/C14 -> 1.9288406 | D37: =(D31*Stundensatz+D35)/D14 -> 1.4996739 | E37: EUR | F37: KV1 = (T1 × S + LK) / V
A38: Nettoeffekt kalkulatorisch | B38: =B33-B35 -> -53.730435 | C38: =C33-C35 -> 96.347826 | D38: =D33-D35 -> 900.3913 | E38: EUR/Monat | F38: NK = KG − LK
A39: Nettoeffekt zahlungswirksam | B39: =B33*B27-B35 -> -20.730435 | C39: =C33*C27-C35 -> -8.6521739 | D39: =D33*D27-D35 -> 382.8913 | E39: EUR/Monat | F39: NZ = r × KG − LK
A40: Einmalkosten zahlungswirksam (extern, Datenschutz, IT-Sicherheit) | B40: =B22*Extern_Stundensatz+B23+B24 -> 2900 | C40: =C22*Extern_Stundensatz+C23+C24 -> 6700 | D40: =D22*Extern_Stundensatz+D23+D24 -> 13300 | E40: EUR | F40: EB = Eh × externer Satz + DS + IT
A41: Interne Einmalstunden bewertet (Schulung, Ist-Aufnahme, Pilot) | B41: =(B25+B26)*Stundensatz -> 630 | C41: =(C25+C26)*Stundensatz -> 1260 | D41: =(D25+D26)*Stundensatz -> 2160 | E41: EUR | F41: EI = (Sh + Ih) × S
A42: Einmalkosten gesamt | B42: =B40+B41 -> 3530 | C42: =C40+C41 -> 7960 | D42: =D40+D41 -> 15460 | E42: EUR | F42: EG = EB + EI
A43: Amortisation kalkulatorisch | B43: =IF(B38>0,B42/B38,"keine") -> keine | C43: =IF(C38>0,C42/C38,"keine") -> 82.617329 | D43: =IF(D38>0,D42/D38,"keine") -> 17.170312 | E43: Monate | F43: AK = EG / NK
A44: Amortisation zahlungswirksam | B44: =IF(B39>0,B40/B39,"keine") -> keine | C44: =IF(C39>0,C40/C39,"keine") -> keine | D44: =IF(D39>0,D40/D39,"keine") -> 34.735707 | E44: Monate | F44: AZ = EB / NZ (interne Stunden sind keine Auszahlung)
A45: Ergebnis nach Betrachtungszeitraum, kalkulatorisch | B45: =Horizont*B38-B42 -> -4819.5304 | C45: =Horizont*C38-C42 -> -5647.6522 | D45: =Horizont*D38-D42 -> 6149.3913 | E45: EUR | F45: H24K = Horizont × NK − EG
A46: Ergebnis nach Betrachtungszeitraum, zahlungswirksam | B46: =Horizont*B39-B40 -> -3397.5304 | C46: =Horizont*C39-C40 -> -6907.6522 | D46: =Horizont*D39-D40 -> -4110.6087 | E46: EUR | F46: H24Z = Horizont × NZ − EB
A47: Nettoeffekt je zusätzlichem Vorgang | B47: =((B15-B16-B17*B18)/60)*Stundensatz-B11 -> 1.1878261 | C47: =((C15-C16-C17*C18)/60)*Stundensatz-C11 -> 1.1878261 | D47: =((D15-D16-D17*D18)/60)*Stundensatz-D11 -> 1.1878261 | E47: EUR | F47: s = ((m0 − m1 − f × mk) / 60) × S − k
A48: Break-even-Volumen kalkulatorisch (aufgerundet) | B48: =IF(B47>0,ROUNDUP((B29*Stundensatz+B19)/B47,0),"nie") -> 106 | C48: =IF(C47>0,ROUNDUP((C29*Stundensatz+C19)/C47,0),"nie") -> 219 | D48: =IF(D47>0,ROUNDUP((D29*Stundensatz+D19)/D47,0),"nie") -> 442 | E48: Vorgänge/Monat | F48: BE = (Wt × S + Sw) / s, aufgerundet
A49: Empfindlichkeit
A50: Nettoeffekt kalkulatorisch mit Arbeitskosten aus Blatt Arbeitskosten | B50: =B32*Stundensatz_KMU-B35 -> -43.312166 | C50: =C32*Stundensatz_KMU-C35 -> 48.992057 | D50: =D32*Stundensatz_KMU-D35 -> 573.6365 | E50: EUR/Monat | F50: NK2 = dT × S_KMU − LK
A51: Amortisation kalkulatorisch mit diesen Arbeitskosten | B51: =IF(B50>0,(B40+(B25+B26)*Stundensatz_KMU)/B50,"keine") -> keine | C51: =IF(C50>0,(C40+(C25+C26)*Stundensatz_KMU)/C50,"keine") -> 154.35587 | D51: =IF(D50>0,(D40+(D25+D26)*Stundensatz_KMU)/D50,"keine") -> 25.762093 | E51: Monate | F51: AK2
A52: Ergebnis nach Betrachtungszeitraum, kalkulatorisch mit diesen Arbeitskosten | B52: =Horizont*B50-(B40+(B25+B26)*Stundensatz_KMU) -> -4370.5977 | C52: =Horizont*C50-(C40+(C25+C26)*Stundensatz_KMU) -> -6386.4022 | D52: =Horizont*D50-(D40+(D25+D26)*Stundensatz_KMU) -> -1010.801 | E52: EUR | F52: H24K2 = Horizont × NK2 − (EB + (Sh + Ih) × S_KMU)
A53: Nettoeffekt kalkulatorisch bei halber Zeitersparnis | B53: =(B30-((B14*(B15+B16)/2+B14*B17*B18)/60+B29))*Stundensatz-B35 -> -98.730435 | C53: =(C30-((C14*(C15+C16)/2+C14*C17*C18)/60+C29))*Stundensatz-C35 -> -128.65217 | D53: =(D30-((D14*(D15+D16)/2+D14*D17*D18)/60+D29))*Stundensatz-D35 -> 0.39130435 | E53: EUR/Monat | F53: NKh = m1 auf die Mitte zwischen m0 und m1 gesetzt
A54: Amortisation kalkulatorisch bei halber Zeitersparnis | B54: =IF(B53>0,B42/B53,"keine") -> keine | C54: =IF(C53>0,C42/C53,"keine") -> keine | D54: =IF(D53>0,D42/D53,"keine") -> 39508.889 | E54: Monate | F54: AKh
A55: Nettoeffekt kalkulatorisch bei doppelter Korrekturquote | B55: =(B30-((B14*B16+B14*2*B17*B18)/60+B29))*Stundensatz-B35 -> -71.730435 | C55: =(C30-((C14*C16+C14*2*C17*C18)/60+C29))*Stundensatz-C35 -> 6.3478261 | D55: =(D30-((D14*D16+D14*2*D17*D18)/60+D29))*Stundensatz-D35 -> 540.3913 | E55: EUR/Monat | F55: NKf = f × 2
A56: Nettoeffekt kalkulatorisch bei höheren KI-Preisen und schwächerem Euro | B56: =B33-(B34*Preisfaktor_Szenario*USD_je_EUR/USD_je_EUR_Szenario+B19) -> -54.2 | C56: =C33-(C34*Preisfaktor_Szenario*USD_je_EUR/USD_je_EUR_Szenario+C19) -> 94 | D56: =D33-(D34*Preisfaktor_Szenario*USD_je_EUR/USD_je_EUR_Szenario+D19) -> 891 | E56: EUR/Monat | F56: NKp = KI-Kosten × Faktor, umgerechnet zum Szenariokurs
A57: Nettoeffekt kalkulatorisch mit Denk-Tokens laut Parameter | B57: =B38-B14*(B12-B11) -> -54.252174 | C57: =C38-C14*(C12-C11) -> 93.73913 | D57: =D38-D14*(D12-D11) -> 889.95652 | E57: EUR/Monat | F57: NKd = NK − V × (kD − k)
A58: Nettoeffekt kalkulatorisch, Wartung und Neutest durch Dienstleister | B58: =B38-B29*(Extern_Stundensatz-Stundensatz) -> -182.06377 | C58: =C38-C29*(Extern_Stundensatz-Stundensatz) -> -160.31884 | D58: =D38-D29*(Extern_Stundensatz-Stundensatz) -> 405.3913 | E58: EUR/Monat | F58: NKx = Wartungsstunden mit externem statt internem Satz
A59: Amortisation kalkulatorisch, Wartung durch Dienstleister | B59: =IF(B58>0,B42/B58,"keine") -> keine | C59: =IF(C58>0,C42/C58,"keine") -> keine | D59: =IF(D58>0,D42/D58,"keine") -> 38.135993 | E59: Monate | F59: AKx
A60: Mindestvolumen für kalkulatorische Amortisation im Betrachtungszeitraum | B60: =IF(B47>0,ROUNDUP((B42/Horizont+B29*Stundensatz+B19)/B47,0),"nie") -> 230 | C60: =IF(C47>0,ROUNDUP((C42/Horizont+C29*Stundensatz+C19)/C47,0),"nie") -> 499 | D60: =IF(D47>0,ROUNDUP((D42/Horizont+D29*Stundensatz+D19)/D47,0),"nie") -> 985 | E60: Vorgänge/Monat | F60: V24 = (EG / Horizont + Wt × S + Sw) / s, aufgerundet; übrige Annahmen der Spalte
A61: Variante: heute gründliche Prüfung
A62: Minuten je AB bei gründlicher Prüfung heute | B62: 6 | C62: 6 | D62: 6 | E62: min | F62: m0G: Annahme
A63: Nettoeffekt kalkulatorisch gegenüber gründlicher Prüfung | B63: =(B14*B62/60-B31)*Stundensatz-B35 -> 81.269565 | C63: =(C14*C62/60-C31)*Stundensatz-C35 -> 771.34783 | D63: =(D14*D62/60-D31)*Stundensatz-D35 -> 3600.3913 | E63: EUR/Monat | F63: NKG
A64: Amortisation kalkulatorisch gegenüber gründlicher Prüfung | B64: =IF(B63>0,B42/B63,"keine") -> 43.435694 | C64: =IF(C63>0,C42/C63,"keine") -> 10.319599 | D64: =IF(D63>0,D42/D63,"keine") -> 4.2939777 | E64: Monate | F64: AKG
A65: Zusatzeffekt: bisher übersehene Abweichungen
A66: Nötiger Wert zusätzlich erkannter Abweichungen je Monat für zahlungswirksame Amortisation in 12 Monaten | B66: =MAX(0,B40/12-B39) -> 262.3971 | C66: =MAX(0,C40/12-C39) -> 566.98551 | D66: =MAX(0,D40/12-D39) -> 725.44203 | E66: EUR/Monat | F66: RS = MAX(0; EB / 12 − NZ)
A67: KI-Kosten je AB mit Batch (Vergleich) | B67: =(B6*INDEX(Preise!$B$5:$B$17,MATCH(B9,Preise!$A$5:$A$17,0))+(B7+B8)*INDEX(Preise!$C$5:$C$17,MATCH(B9,Preise!$A$5:$A$17,0)))/1000000*Batchfaktor/USD_je_EUR -> 0.0060869565 | C67: =(C6*INDEX(Preise!$B$5:$B$17,MATCH(C9,Preise!$A$5:$A$17,0))+(C7+C8)*INDEX(Preise!$C$5:$C$17,MATCH(C9,Preise!$A$5:$A$17,0)))/1000000*Batchfaktor/USD_je_EUR -> 0.0060869565 | D67: =(D6*INDEX(Preise!$B$5:$B$17,MATCH(D9,Preise!$A$5:$A$17,0))+(D7+D8)*INDEX(Preise!$C$5:$C$17,MATCH(D9,Preise!$A$5:$A$17,0)))/1000000*Batchfaktor/USD_je_EUR -> 0.0060869565 | E67: EUR | F67: kB
A68: Nettoeffekt je zusätzlicher AB gegenüber gründlicher Prüfung | B68: =((B62-B16-B17*B18)/60)*Stundensatz-B11 -> 3.4378261 | C68: =((C62-C16-C17*C18)/60)*Stundensatz-C11 -> 3.4378261 | D68: =((D62-D16-D17*D18)/60)*Stundensatz-D11 -> 3.4378261 | E68: EUR | F68: sG
A69: Break-even kalkulatorisch gegenüber gründlicher Prüfung (aufgerundet) | B69: =IF(B68>0,ROUNDUP((B29*Stundensatz+B19)/B68,0),"nie") -> 37 | C69: =IF(C68>0,ROUNDUP((C29*Stundensatz+C19)/C68,0),"nie") -> 76 | D69: =IF(D68>0,ROUNDUP((D29*Stundensatz+D19)/D68,0),"nie") -> 153 | E69: AB/Monat | F69: BEG
A70: Mindestvolumen für Amortisation im Betrachtungszeitraum, gegenüber gründlicher Prüfung | B70: =IF(B68>0,ROUNDUP((B42/Horizont+B29*Stundensatz+B19)/B68,0),"nie") -> 80 | C70: =IF(C68>0,ROUNDUP((C42/Horizont+C29*Stundensatz+C19)/C68,0),"nie") -> 173 | D70: =IF(D68>0,ROUNDUP((D42/Horizont+D29*Stundensatz+D19)/D68,0),"nie") -> 341 | E70: AB/Monat | F70: V24G

Sheet Fall C
A1: Praxisfall C (Kapitel 9): Unvollständige Kundenanfragen erkennen und nachfragen
A2: Alle Werte sind Annahmen. Entwürfe werden immer von einem Menschen geprüft und versendet.
A4: Position | B4: Kleinbetrieb | C4: Mittlerer Betrieb | D4: Betrieb mit hohem Volumen | E4: Einheit | F4: Formel / Erläuterung
A5: KI-Kosten je Vorgang
A6: Input-Tokens je Anfrage (Anweisung, Pflichtangaben-Liste, E-Mail, Anhangsliste) | B6: 2000 | C6: =$B6 -> 2000 | D6: =$B6 -> 2000 | E6: Tokens | F6: ti: Annahme
A7: Output-Tokens (Prüfergebnis und Rückfrage-Entwurf) | B7: 300 | C7: =$B7 -> 300 | D7: =$B7 -> 300 | E7: Tokens | F7: to: Annahme
A8: Denk-Tokens je Anfrage | B8: 0 | C8: =$B8 -> 0 | D8: =$B8 -> 0 | E8: Tokens | F8: dt: 0: Denken abgeschaltet (Haiku 5.5: thinking disabled, Effort höchstens high)
A9: Modell | B9: Claude Haiku 5.5 | C9: =$B9 -> Claude Haiku 5.5 | D9: =$B9 -> Claude Haiku 5.5 | F9: M: Auswahl aus Blatt Preise
A10: Vergleichsmodell | B10: Claude Sonnet 5.5 | C10: =$B10 -> Claude Sonnet 5.5 | D10: =$B10 -> Claude Sonnet 5.5 | F10: M2: Auswahl aus Blatt Preise
A11: KI-Kosten je Vorgang | B11: =(B6*INDEX(Preise!$B$5:$B$17,MATCH(B9,Preise!$A$5:$A$17,0))+(B7+B8)*INDEX(Preise!$C$5:$C$17,MATCH(B9,Preise!$A$5:$A$17,0)))/1000000/USD_je_EUR -> 0.00030434783 | C11: =(C6*INDEX(Preise!$B$5:$B$17,MATCH(C9,Preise!$A$5:$A$17,0))+(C7+C8)*INDEX(Preise!$C$5:$C$17,MATCH(C9,Preise!$A$5:$A$17,0)))/1000000/USD_je_EUR -> 0.00030434783 | D11: =(D6*INDEX(Preise!$B$5:$B$17,MATCH(D9,Preise!$A$5:$A$17,0))+(D7+D8)*INDEX(Preise!$C$5:$C$17,MATCH(D9,Preise!$A$5:$A$17,0)))/1000000/USD_je_EUR -> 0.00030434783 | E11: EUR | F11: k
A12: KI-Kosten je Vorgang mit Denk-Tokens laut Parameter (Empfindlichkeit) | B12: =B11+Denk_Tokens_Szenario*INDEX(Preise!$C$5:$C$17,MATCH(B9,Preise!$A$5:$A$17,0))/1000000/USD_je_EUR -> 0.00073913043 | C12: =C11+Denk_Tokens_Szenario*INDEX(Preise!$C$5:$C$17,MATCH(C9,Preise!$A$5:$A$17,0))/1000000/USD_je_EUR -> 0.00073913043 | D12: =D11+Denk_Tokens_Szenario*INDEX(Preise!$C$5:$C$17,MATCH(D9,Preise!$A$5:$A$17,0))/1000000/USD_je_EUR -> 0.00073913043 | E12: EUR | F12: kD: k zuzüglich Denk_Tokens_Szenario zum Output-Preis des Modells
A13: Eingaben je Szenario
A14: Kundenanfragen je Monat | B14: 100 | C14: 400 | D14: 1500 | E14: Anzahl | F14: V: Annahme
A15: Minuten je Anfrage ohne KI (prüfen, ggf. Rückfrage schreiben) | B15: 5 | C15: 5 | D15: 5 | E15: min | F15: m0: Annahme; Durchschnitt über vollständige und unvollständige Anfragen
A16: Minuten je Anfrage mit KI (Ergebnis und Entwurf prüfen, senden) | B16: 2 | C16: 2 | D16: 2 | E16: min | F16: m1: Annahme
A17: Anteil unbrauchbarer Ergebnisse | B17: 0.15 | C17: 0.15 | D17: 0.15 | E17: % | F17: f: Annahme; im Pilot messen
A18: Minuten je unbrauchbarem Ergebnis | B18: 4 | C18: 4 | D18: 4 | E18: min | F18: mk: Annahme
A19: Feste Software- und Plattformkosten | B19: 20 | C19: 40 | D19: 100 | E19: EUR/Monat | F19: Sw: Annahme
A20: Wartung und Kontrolle (Stichproben, Anpassungen) | B20: 1 | C20: 3 | D20: 6 | E20: h/Monat | F20: Wh: Annahme
A21: Neutest nach Modell- oder Anbieterwechsel | B21: 4 | C21: 8 | D21: 12 | E21: h/Jahr | F21: NT: Annahme
A22: Einrichtung durch Dienstleister | B22: 15 | C22: 30 | D22: 60 | E22: h | F22: Eh: Annahme; bewertet mit externem Stundensatz aus Blatt Parameter
A23: Datenschutz und Recht, einmalig (AVV-Prüfung, Verzeichnis, Information, ggf. Betriebsrat) | B23: 400 | C23: 600 | D23: 1000 | E23: EUR | F23: DS: Annahme
A24: IT-Sicherheit, einmalig (Zugänge, Rechte, Protokollierung) | B24: 200 | C24: 400 | D24: 800 | E24: EUR | F24: IT: Annahme
A25: Schulung | B25: 2 | C25: 4 | D25: 8 | E25: h gesamt | F25: Sh: Annahme
... A27: Zahlungswirksam realisierbarer Anteil der gesparten Zeit | B27: 0 | C27: 0.3 | D27: 0.5 | E27: % | F27: r: Annahme. 0 % = Zeit wird anders genutzt, keine Ausgabe sinkt. Anteil nur ansetzen, wenn Überstunden, Aushilfen oder Fremdleistungen tatsächlich wegfallen.
A28: Ergebnisse
A29: Wartung gesamt inkl. Neutest nach Modellwechseln | B29: =B20+B21/12 -> 1.3333333 | C29: =C20+C21/12 -> 3.6666667 | D29: =D20+D21/12 -> 7 | E29: h/Monat | F29: Wt = Wh + NT / 12
A30: Arbeitszeit ohne KI | B30: =B14*B15/60 -> 8.3333333 | C30: =C14*C15/60 -> 33.333333 | D30: =D14*D15/60 -> 125 | E30: h/Monat | F30: T0 = V × m0 / 60
A31: Arbeitszeit mit KI inkl. Korrekturen und Wartung | B31: =(B14*B16+B14*B17*B18)/60+B29 -> 5.6666667 | C31: =(C14*C16+C14*C17*C18)/60+C29 -> 21 | D31: =(D14*D16+D14*D17*D18)/60+D29 -> 72 | E31: h/Monat | F31: T1 = (V × m1 + V × f × mk) / 60 + Wt
A32: Frei werdende Arbeitszeit (Kapazitätsgewinn) | B32: =B30-B31 -> 2.6666667 | C32: =C30-C31 -> 12.333333 | D32: =D30-D31 -> 53 | E32: h/Monat | F32: dT = T0 − T1
A33: Kapazitätsgewinn bewertet | B33: =B32*Stundensatz -> 120 | C33: =C32*Stundensatz -> 555 | D33: =D32*Stundensatz -> 2385 | E33: EUR/Monat | F33: KG = dT × S
A34: KI-Kosten im Monat | B34: =B14*B11 -> 0.030434783 | C34: =C14*C11 -> 0.12173913 | D34: =D14*D11 -> 0.45652174 | E34: EUR/Monat | F34: KM = V × k
A35: Laufende zahlungswirksame Kosten | B35: =B34+B19 -> 20.030435 | C35: =C34+C19 -> 40.121739 | D35: =D34+D19 -> 100.45652 | E35: EUR/Monat | F35: LK = V × k + Software
A36: Kosten je Vorgang ohne KI | B36: =B15/60*Stundensatz -> 3.75 | C36: =C15/60*Stundensatz -> 3.75 | D36: =D15/60*Stundensatz -> 3.75 | E36: EUR | F36: KV0 = m0 / 60 × S
A37: Kosten je Vorgang mit KI | B37: =(B31*Stundensatz+B35)/B14 -> 2.7503043 | C37: =(C31*Stundensatz+C35)/C14 -> 2.4628043 | D37: =(D31*Stundensatz+D35)/D14 -> 2.226971 | E37: EUR | F37: KV1 = (T1 × S + LK) / V
A38: Nettoeffekt kalkulatorisch | B38: =B33-B35 -> 99.969565 | C38: =C33-C35 -> 514.87826 | D38: =D33-D35 -> 2284.5435 | E38: EUR/Monat | F38: NK = KG − LK
A39: Nettoeffekt zahlungswirksam | B39: =B33*B27-B35 -> -20.030435 | C39: =C33*C27-C35 -> 126.37826 | D39: =D33*D27-D35 -> 1092.0435 | E39: EUR/Monat | F39: NZ = r × KG − LK
A40: Einmalkosten zahlungswirksam (extern, Datenschutz, IT-Sicherheit) | B40: =B22*Extern_Stundensatz+B23+B24 -> 2100 | C40: =C22*Extern_Stundensatz+C23+C24 -> 4000 | D40: =D22*Extern_Stundensatz+D23+D24 -> 7800 | E40: EUR | F40: EB = Eh × externer Satz + DS + IT
A41: Interne Einmalstunden bewertet (Schulung, Ist-Aufnahme, Pilot) | B41: =(B25+B26)*Stundensatz -> 450 | C41: =(C25+C26)*Stundensatz -> 900 | D41: =(D25+D26)*Stundensatz -> 1710 | E41: EUR | F41: EI = (Sh + Ih) × S
A42: Einmalkosten gesamt | B42: =B40+B41 -> 2550 | C42: =C40+C41 -> 4900 | D42: =D40+D41 -> 9510 | E42: EUR | F42: EG = EB + EI
A43: Amortisation kalkulatorisch | B43: =IF(B38>0,B42/B38,"keine") -> 25.507763 | C43: =IF(C38>0,C42/C38,"keine") -> 9.5168128 | D43: =IF(D38>0,D42/D38,"keine") -> 4.1627573 | E43: Monate | F43: AK = EG / NK
A44: Amortisation zahlungswirksam | B44: =IF(B39>0,B40/B39,"keine") -> keine | C44: =IF(C39>0,C40/C39,"keine") -> 31.651013 | D44: =IF(D39>0,D40/D39,"keine") -> 7.1425728 | E44: Monate | F44: AZ = EB / NZ (interne Stunden sind keine Auszahlung)
A45: Ergebnis nach Betrachtungszeitraum, kalkulatorisch | B45: =Horizont*B38-B42 -> -150.73043 | C45: =Horizont*C38-C42 -> 7457.0783 | D45: =Horizont*D38-D42 -> 45319.043 | E45: EUR | F45: H24K = Horizont × NK − EG
A46: Ergebnis nach Betrachtungszeitraum, zahlungswirksam | B46: =Horizont*B39-B40 -> -2580.7304 | C46: =Horizont*C39-C40 -> -966.92174 | D46: =Horizont*D39-D40 -> 18409.043 | E46: EUR | F46: H24Z = Horizont × NZ − EB
A47: Nettoeffekt je zusätzlichem Vorgang | B47: =((B15-B16-B17*B18)/60)*Stundensatz-B11 -> 1.7996957 | C47: =((C15-C16-C17*C18)/60)*Stundensatz-C11 -> 1.7996957 | D47: =((D15-D16-D17*D18)/60)*Stundensatz-D11 -> 1.7996957 | E47: EUR | F47: s = ((m0 − m1 − f × mk) / 60) × S − k
A48: Break-even-Volumen kalkulatorisch (aufgerundet) | B48: =IF(B47>0,ROUNDUP((B29*Stundensatz+B19)/B47,0),"nie") -> 45 | C48: =IF(C47>0,ROUNDUP((C29*Stundensatz+C19)/C47,0),"nie") -> 114 | D48: =IF(D47>0,ROUNDUP((D29*Stundensatz+D19)/D47,0),"nie") -> 231 | E48: Vorgänge/Monat | F48: BE = (Wt × S + Sw) / s, aufgerundet
A49: Empfindlichkeit
A50: Nettoeffekt kalkulatorisch mit Arbeitskosten aus Blatt Arbeitskosten | B50: =B32*Stundensatz_KMU-B35 -> 62.08495 | C50: =C32*Stundensatz_KMU-C35 -> 339.66191 | D50: =D32*Stundensatz_KMU-D35 -> 1531.5867 | E50: EUR/Monat | F50: NK2 = dT × S_KMU − LK
A51: Amortisation kalkulatorisch mit diesen Arbeitskosten | B51: =IF(B50>0,(B40+(B25+B26)*Stundensatz_KMU)/B50,"keine") -> 38.784483 | C51: =IF(C50>0,(C40+(C25+C26)*Stundensatz_KMU)/C50,"keine") -> 13.589588 | D51: =IF(D50>0,(D40+(D25+D26)*Stundensatz_KMU)/D50,"keine") -> 5.8567654 | E51: Monate | F51: AK2
A52: Ergebnis nach Betrachtungszeitraum, kalkulatorisch mit diesen Arbeitskosten | B52: =Horizont*B50-(B40+(B25+B26)*Stundensatz_KMU) -> -917.8939 | C52: =Horizont*C50-(C40+(C25+C26)*Stundensatz_KMU) -> 3536.0206 | D52: =Horizont*D50-(D40+(D25+D26)*Stundensatz_KMU) -> 27787.938 | E52: EUR | F52: H24K2 = Horizont × NK2 − (EB + (Sh + Ih) × S_KMU)
A53: Nettoeffekt kalkulatorisch bei halber Zeitersparnis | B53: =(B30-((B14*(B15+B16)/2+B14*B17*B18)/60+B29))*Stundensatz-B35 -> -12.530435 | C53: =(C30-((C14*(C15+C16)/2+C14*C17*C18)/60+C29))*Stundensatz-C35 -> 64.878261 | D53: =(D30-((D14*(D15+D16)/2+D14*D17*D18)/60+D29))*Stundensatz-D35 -> 597.04348 | E53: EUR/Monat | F53: NKh = m1 auf die Mitte zwischen m0 und m1 gesetzt
A54: Amortisation kalkulatorisch bei halber Zeitersparnis | B54: =IF(B53>0,B42/B53,"keine") -> keine | C54: =IF(C53>0,C42/C53,"keine") -> 75.526069 | D54: =IF(D53>0,D42/D53,"keine") -> 15.928488 | E54: Monate | F54: AKh
A55: Nettoeffekt kalkulatorisch bei doppelter Korrekturquote | B55: =(B30-((B14*B16+B14*2*B17*B18)/60+B29))*Stundensatz-B35 -> 54.969565 | C55: =(C30-((C14*C16+C14*2*C17*C18)/60+C29))*Stundensatz-C35 -> 334.87826 | D55: =(D30-((D14*D16+D14*2*D17*D18)/60+D29))*Stundensatz-D35 -> 1609.5435 | E55: EUR/Monat | F55: NKf = f × 2
A56: Nettoeffekt kalkulatorisch bei höheren KI-Preisen und schwächerem Euro | B56: =B33-(B34*Preisfaktor_Szenario*USD_je_EUR/USD_je_EUR_Szenario+B19) -> 99.95 | C56: =C33-(C34*Preisfaktor_Szenario*USD_je_EUR/USD_je_EUR_Szenario+C19) -> 514.8 | D56: =D33-(D34*Preisfaktor_Szenario*USD_je_EUR/USD_je_EUR_Szenario+D19) -> 2284.25 | E56: EUR/Monat | F56: NKp = KI-Kosten × Faktor, umgerechnet zum Szenariokurs
A57: Nettoeffekt kalkulatorisch mit Denk-Tokens laut Parameter | B57: =B38-B14*(B12-B11) -> 99.926087 | C57: =C38-C14*(C12-C11) -> 514.70435 | D57: =D38-D14*(D12-D11) -> 2283.8913 | E57: EUR/Monat | F57: NKd = NK − V × (kD − k)
A58: Nettoeffekt kalkulatorisch, Wartung und Neutest durch Dienstleister | B58: =B38-B29*(Extern_Stundensatz-Stundensatz) -> 26.636232 | C58: =C38-C29*(Extern_Stundensatz-Stundensatz) -> 313.21159 | D58: =D38-D29*(Extern_Stundensatz-Stundensatz) -> 1899.5435 | E58: EUR/Monat | F58: NKx = Wartungsstunden mit externem statt internem Satz
A59: Amortisation kalkulatorisch, Wartung durch Dienstleister | B59: =IF(B58>0,B42/B58,"keine") -> 95.734262 | C59: =IF(C58>0,C42/C58,"keine") -> 15.644376 | D59: =IF(D58>0,D42/D58,"keine") -> 5.0064661 | E59: Monate | F59: AKx
A60: Mindestvolumen für kalkulatorische Amortisation im Betrachtungszeitraum | B60: =IF(B47>0,ROUNDUP((B42/Horizont+B29*Stundensatz+B19)/B47,0),"nie") -> 104 | C60: =IF(C47>0,ROUNDUP((C42/Horizont+C29*Stundensatz+C19)/C47,0),"nie") -> 228 | D60: =IF(D47>0,ROUNDUP((D42/Horizont+D29*Stundensatz+D19)/D47,0),"nie") -> 451 | E60: Vorgänge/Monat | F60: V24 = (EG / Horizont + Wt × S + Sw) / s, aufgerundet; übrige Annahmen der Spalte
A61: Zusatzeffekt: schnellere Angebote
A62: Nötiger zusätzlicher Deckungsbeitrag je Monat für zahlungswirksame Amortisation in 12 Monaten | B62: =MAX(0,B40/12-B39) -> 195.03043 | C62: =MAX(0,C40/12-C39) -> 206.95507 | D62: =MAX(0,D40/12-D39) -> 0 | E62: EUR/Monat | F62: RS = MAX(0; EB / 12 − NZ)
A63: KI-Kosten im Monat mit Sonnet 5.5 statt Haiku 5.5 (USD, Vergleich) | B63: =B14*(B6*INDEX(Preise!$B$5:$B$17,MATCH(B10,Preise!$A$5:$A$17,0))+(B7+B8)*INDEX(Preise!$C$5:$C$17,MATCH(B10,Preise!$A$5:$A$17,0)))/1000000 -> 0.7 | C63: =C14*(C6*INDEX(Preise!$B$5:$B$17,MATCH(C10,Preise!$A$5:$A$17,0))+(C7+C8)*INDEX(Preise!$C$5:$C$17,MATCH(C10,Preise!$A$5:$A$17,0)))/1000000 -> 2.8 | D63: =D14*(D6*INDEX(Preise!$B$5:$B$17,MATCH(D10,Preise!$A$5:$A$17,0))+(D7+D8)*INDEX(Preise!$C$5:$C$17,MATCH(D10,Preise!$A$5:$A$17,0)))/1000000 -> 10.5 | E63: USD/Monat | F63: KS = Preise des Vergleichsmodells laut Blatt Preise

Sheet Stichprobe
A1: Stichprobengröße (Kapitel 11)
A2: Wahrscheinlichkeit, in n geprüften Vorgängen keinen einzigen Fehler zu finden: P = (1 − a)^n (Anhang A)
A4: geprüfte Vorgänge n \ Fehleranteil a | B4: 0.01 | C4: 0.05 | D4: 0.1
A5: 10 | B5: =(1-B$4)^$A5 -> 0.90438208 | C5: =(1-C$4)^$A5 -> 0.59873694 | D5: =(1-D$4)^$A5 -> 0.34867844
A6: 20 | B6: =(1-B$4)^$A6 -> 0.81790694 | C6: =(1-C$4)^$A6 -> 0.35848592 | D6: =(1-D$4)^$A6 -> 0.12157665
A7: 30 | B7: =(1-B$4)^$A7 -> 0.73970037 | C7: =(1-C$4)^$A7 -> 0.21463876 | D7: =(1-D$4)^$A7 -> 0.042391158
A8: 50 | B8: =(1-B$4)^$A8 -> 0.60500607 | C8: =(1-C$4)^$A8 -> 0.076944975 | D8: =(1-D$4)^$A8 -> 0.0051537752
A10: gewünschte Sicherheit c | B10: 0.9
A11: Nötige Stichprobe, um mit Sicherheit c mindestens einen Fehler zu sehen
A12: Fehleranteil a | B12: Vorgänge
A13: 0.02 | B13: =ROUNDUP(LN(1-$B$10)/LN(1-A13),0) -> 114
A14: 0.05 | B14: =ROUNDUP(LN(1-$B$10)/LN(1-A14),0) -> 45
A15: 0.1 | B15: =ROUNDUP(LN(1-$B$10)/LN(1-A15),0) -> 22
